Workbook
Name Dashboard_Categories: Dashboard_Lists!$C$2:$C$11
Name Dashboard_Departments: Dashboard_Lists!$B$2:$B$9
Name Dashboard_Months: Dashboard_Lists!$A$2:$A$26

Sheet Dashboard
A1: FIN-W5-005 | FINANCIAL INTELLIGENCE DASHBOARD
A2: Corporate Finance • FP&A • Receivables • Cash Flow • Risk Management
A3: EXPENSE FILTER / SELECTED VALUES
A4: Dropdown for filter | C4: Month | D4: 45474 | F4: Department | G4: All Departments | I4: Category | J4: All Categories
A6: SELECTED MONTH EXPENSE | C6: SELECTED DEPARTMENT EXPENSE | E6: SELECTED CATEGORY EXPENSE | G6: CURRENT FILTERED EXPENSE | I6: Collection Efficiency | K6: Outstanding AR
A7: =IF(D4="All Months",SUM(Clean_Expenses!$E:$E),SUMIFS(Clean_Expenses!$E:$E,Clean_Expenses!$B:$B,">="&D4,Clean_Expenses!$B:$B,"<"&EDATE(D4,1))) -> 924314.79 | C7: =IF(G4="All Departments",SUM(Clean_Expenses!$E:$E),SUMIFS(Clean_Expenses!$E:$E,Clean_Expenses!$C:$C,G4)) -> 22048782 | E7: =IF(J4="All Categories",SUM(Clean_Expenses!$E:$E),SUMIFS(Clean_Expenses!$E:$E,Clean_Expenses!$D:$D,J4)) -> 22048782 | G7: =IF(AND(D4="All Months",G4="All Departments",J4="All Categories"),SUM(Clean_Expenses!$E:$E),SUMIFS(Clean_Expenses!$E:$E,Clean_Expenses!$C:$C,IF(G4="All Departments","<>",G4),Clean_Expenses!$D:$D,IF(J4="All Categories","<>",J4),Clean_Expenses!$B:$B,IF(D4="All Months","<>",">="&D4))) -> 16205859 | I7: =Revenue_Collections!E2 -> 0 | K7: {=IF($D$4="All Months",SUM(Clean_AR_Data!$H:$H),SUMPRODUCT((Clean_AR_Data!$C$2:$C$1642<=EOMONTH($D$4,0))*((Clean_AR_Data!$E$2:$E$1642="")+(Clean_AR_Data!$E$2:$E$1642>EOMONTH($D$4,0))>0)*(Clean_AR_Data!$F$2:$F$1642-IF((Clean_AR_Data!$E$2:$E$1642<>"")*(Clean_AR_Data!$E$2:$E$1642<=EOMONTH($D$4,0)),Clean_AR_Data!$G$2:$G$1642,0))))} -> 7777501.2
A8: Overdue Receivables | D8: Receivable Days | F8: Liquidity Risk Score | H8: Liquidity Risk Level | J8: Revenue collection
A10: =IF($D$4="All Months",SUMPRODUCT((Clean_AR_Data!$D$2:$D$1642<TODAY())*((Clean_AR_Data!$E$2:$E$1642="")+(Clean_AR_Data!$E$2:$E$1642>TODAY())>0)*(Clean_AR_Data!$F$2:$F$1642-IF((Clean_AR_Data!$E$2:$E$1642<>"")*(Clean_AR_Data!$E$2:$E$1642<=TODAY()),Clean_AR_Data!$G$2:$G$1642,0))),SUMPRODUCT((Clean_AR_Data!$C$2:$C$1642<=EOMONTH($D$4,0))*(Clean_AR_Data!$D$2:$D$1642<=EOMONTH($D$4,0))*((Clean_AR_Data!$E$2:$E$1642="")+(Clean_AR_Data!$E$2:$E$1642>EOMONTH($D$4,0))>0)*(Clean_AR_Data!$F$2:$F$1642-IF((Clean_AR_Data!$E$2:$E$1642<>"")*(Clean_AR_Data!$E$2:$E$1642<=EOMONTH($D$4,0)),Clean_AR_Data!$G$2:$G$1642,0)))) -> 4759299.8 | D10: =IF($D$4="All Months",KPI_Summary!$B$2,IFERROR(#REF!/SUMIFS(Revenue_Collections!$B:$B,Revenue_Collections!$A:$A,$D$4)*DAY(EOMONTH($D$4,0)),0)) -> 0 | F10: =IF($D$4="All Months",KPI_Summary!$B$11,MIN(100,ROUND((IF($D$10>90,40,IF($D$10>60,30,IF($D$10>45,20,IF($D$10>30,10,0)))))+(IFERROR(IF($A$10/#REF!>50%,35,IF($A$10/#REF!>30%,25,IF($A$10/#REF!>15%,15,IF($A$10/#REF!>5%,8,0)))),0))+(IFERROR(IF(SUMIFS(Revenue_Collections!$E:$E,Revenue_Collections!$A:$A,$D$4)<50%,25,IF(SUMIFS(Revenue_Collections!$E:$E,Revenue_Collections!$A:$A,$D$4)<70%,18,IF(SUMIFS(Revenue_Collections!$E:$E,Revenue_Collections!$A:$A,$D$4)<85%,10,0))),0)),0))) -> 0 | H10: =IF($F$10>=70,"High",IF($F$10>=40,"Medium","Low")) -> Low | J10: =Revenue_Collections!C3 -> 1498657.4
A27: REVENUE COLLECTION | F27: CASH FORECAST

Sheet Data_Dictionary
A1: Field | B1: Data Type | C1: Business Meaning | D1: Validation / Calculation
A2: Invoice_ID | B2: Text | C2: Unique invoice identifier | D2: Must be unique
A3: Customer_ID | B3: Text | C3: Customer reference | D3: Must exist in Customer_Master
A4: Invoice_Amount | B4: Numeric | C4: Billed revenue | D4: Must be >= 0
A5: Amount_Collected | B5: Numeric | C5: Cash received | D5: Must be <= Invoice_Amount
A6: Due_Date | B6: Date | C6: Payment deadline | D6: Must be >= Invoice_Date
A7: Payment_Date | B7: Date | C7: Actual collection date | D7: Blank when unpaid
A8: Outstanding_Amount | B8: Numeric | C8: Uncollected balance | D8: Invoice_Amount - Amount_Collected
A9: Payment_Delay_Days | B9: Numeric | C9: Days late/early | D9: Payment_Date - Due_Date
A10: Budget | B10: Numeric | C10: Approved spending | D10: Must be >= 0
A11: Actual_Expense | B11: Numeric | C11: Actual spending | D11: Must be >= 0
A12: Variance | B12: Numeric | C12: Budget variance | D12: Actual - Budget
A13: Variance_% | B13: Percentage | C13: Relative budget variance | D13: (Actual-Budget)/Budget

Sheet Clean_AR_Data
A1: Invoice_ID | B1: Customer_ID | C1: Invoice_Date | D1: Due_Date | E1: Payment_Date | F1: Invoice_Amount | G1: Amount_Collected | H1: Outstanding_Amount | I1: Payment_Delay_Days | J1: Payment_Status | K1: Age_Days | L1: Age_Bucket | M1: Invoice_Month | N1: Collection_Month
A2: INV-100001 | B2: CUST-036 | C2: 45301 | D2: 45331 | E2: 45331 | F2: 41621.69 | G2: 41621.69 | H2: =MAX(0,F2-G2) -> 0 | I2: =IF(E2="","",MAX(0,E2-D2)) -> 0 | J2: =IF(H2=0,"Paid",IF(D2<TODAY(),"Overdue","Open")) -> Paid | K2: =IF(H2=0,0,MAX(0,TODAY()-D2)) -> 0 | L2: =IF(H2=0,"Paid",IF(K2<=30,"0-30 Days",IF(K2<=60,"31-60 Days",IF(K2<=90,"61-90 Days",IF(K2<=120,"91-120 Days","120+ Days"))))) -> Paid | M2: 45292 | N2: 45323
A3: INV-100002 | B3: CUST-006 | C3: 45314 | D3: 45344 | F3: 15198.08 | G3: 0 | H3: =MAX(0,F3-G3) -> 15198.08 | I3: =IF(E3="","",MAX(0,E3-D3)) | J3: =IF(H3=0,"Paid",IF(D3<TODAY(),"Overdue","Open")) -> Overdue | K3: =IF(H3=0,0,MAX(0,TODAY()-D3)) -> 912 | L3: =IF(H3=0,"Paid",IF(K3<=30,"0-30 Days",IF(K3<=60,"31-60 Days",IF(K3<=90,"61-90 Days",IF(K3<=120,"91-120 Days","120+ Days"))))) -> 120+ Days | M3: 45292
A4: INV-100003 | B4: CUST-039 | C4: 45295 | D4: 45325 | E4: 45333 | F4: 44550.46 | G4: 44550.46 | H4: =MAX(0,F4-G4) -> 0 | I4: =IF(E4="","",MAX(0,E4-D4)) -> 8 | J4: =IF(H4=0,"Paid",IF(D4<TODAY(),"Overdue","Open")) -> Paid | K4: =IF(H4=0,0,MAX(0,TODAY()-D4)) -> 0 | L4: =IF(H4=0,"Paid",IF(K4<=30,"0-30 Days",IF(K4<=60,"31-60 Days",IF(K4<=90,"61-90 Days",IF(K4<=120,"91-120 Days","120+ Days"))))) -> Paid | M4: 45292 | N4: 45323
A5: INV-100004 | B5: CUST-038 | C5: 45299 | D5: 45329 | F5: 65545.95 | G5: 0 | H5: =MAX(0,F5-G5) -> 65545.95 | I5: =IF(E5="","",MAX(0,E5-D5)) | J5: =IF(H5=0,"Paid",IF(D5<TODAY(),"Overdue","Open")) -> Overdue | K5: =IF(H5=0,0,MAX(0,TODAY()-D5)) -> 927 | L5: =IF(H5=0,"Paid",IF(K5<=30,"0-30 Days",IF(K5<=60,"31-60 Days",IF(K5<=90,"61-90 Days",IF(K5<=120,"91-120 Days","120+ Days"))))) -> 120+ Days | M5: 45292
A6: INV-100005 | B6: CUST-006 | C6: 45318 | D6: 45348 | F6: 22453.14 | G6: 0 | H6: =MAX(0,F6-G6) -> 22453.14 | I6: =IF(E6="","",MAX(0,E6-D6)) | J6: =IF(H6=0,"Paid",IF(D6<TODAY(),"Overdue","Open")) -> Overdue | K6: =IF(H6=0,0,MAX(0,TODAY()-D6)) -> 908 | L6: =IF(H6=0,"Paid",IF(K6<=30,"0-30 Days",IF(K6<=60,"31-60 Days",IF(K6<=90,"61-90 Days",IF(K6<=120,"91-120 Days","120+ Days"))))) -> 120+ Days | M6: 45292
A7: INV-100006 | B7: CUST-046 | C7: 45298 | D7: 45328 | F7: 123088.43 | G7: 0 | H7: =MAX(0,F7-G7) -> 123088.43 | I7: =IF(E7="","",MAX(0,E7-D7)) | J7: =IF(H7=0,"Paid",IF(D7<TODAY(),"Overdue","Open")) -> Overdue | K7: =IF(H7=0,0,MAX(0,TODAY()-D7)) -> 928 | L7: =IF(H7=0,"Paid",IF(K7<=30,"0-30 Days",IF(K7<=60,"31-60 Days",IF(K7<=90,"61-90 Days",IF(K7<=120,"91-120 Days","120+ Days"))))) -> 120+ Days | M7: 45292
A8: INV-100007 | B8: CUST-025 | C8: 45304 | D8: 45334 | F8: 23234.42 | G8: 0 | H8: =MAX(0,F8-G8) -> 23234.42 | I8: =IF(E8="","",MAX(0,E8-D8)) | J8: =IF(H8=0,"Paid",IF(D8<TODAY(),"Overdue","Open")) -> Overdue | K8: =IF(H8=0,0,MAX(0,TODAY()-D8)) -> 922 | L8: =IF(H8=0,"Paid",IF(K8<=30,"0-30 Days",IF(K8<=60,"31-60 Days",IF(K8<=90,"61-90 Days",IF(K8<=120,"91-120 Days","120+ Days"))))) -> 120+ Days | M8: 45292
A9: INV-100008 | B9: CUST-048 | C9: 45313 | D9: 45343 | E9: 45349 | F9: 47179.89 | G9: 47179.89 | H9: =MAX(0,F9-G9) -> 0 | I9: =IF(E9="","",MAX(0,E9-D9)) -> 6 | J9: =IF(H9=0,"Paid",IF(D9<TODAY(),"Overdue","Open")) -> Paid | K9: =IF(H9=0,0,MAX(0,TODAY()-D9)) -> 0 | L9: =IF(H9=0,"Paid",IF(K9<=30,"0-30 Days",IF(K9<=60,"31-60 Days",IF(K9<=90,"61-90 Days",IF(K9<=120,"91-120 Days","120+ Days"))))) -> Paid | M9: 45292 | N9: 45323
A10: INV-100009 | B10: CUST-003 | C10: 45318 | D10: 45348 | E10: 45357 | F10: 48792.88 | G10: 48792.88 | H10: =MAX(0,F10-G10) -> 0 | I10: =IF(E10="","",MAX(0,E10-D10)) -> 9 | J10: =IF(H10=0,"Paid",IF(D10<TODAY(),"Overdue","Open")) -> Paid | K10: =IF(H10=0,0,MAX(0,TODAY()-D10)) -> 0 | L10: =IF(H10=0,"Paid",IF(K10<=30,"0-30 Days",IF(K10<=60,"31-60 Days",IF(K10<=90,"61-90 Days",IF(K10<=120,"91-120 Days","120+ Days"))))) -> Paid | M10: 45292 | N10: 45352
A11: INV-100010 | B11: CUST-011 | C11: 45317 | D11: 45347 | F11: 18904.1 | G11: 0 | H11: =MAX(0,F11-G11) -> 18904.1 | I11: =IF(E11="","",MAX(0,E11-D11)) | J11: =IF(H11=0,"Paid",IF(D11<TODAY(),"Overdue","Open")) -> Overdue | K11: =IF(H11=0,0,MAX(0,TODAY()-D11)) -> 909 | L11: =IF(H11=0,"Paid",IF(K11<=30,"0-30 Days",IF(K11<=60,"31-60 Days",IF(K11<=90,"61-90 Days",IF(K11<=120,"91-120 Days","120+ Days"))))) -> 120+ Days | M11: 45292
A12: INV-100011 | B12: CUST-030 | C12: 45294 | D12: 45324 | F12: 41689.12 | G12: 0 | H12: =MAX(0,F12-G12) -> 41689.12 | I12: =IF(E12="","",MAX(0,E12-D12)) | J12: =IF(H12=0,"Paid",IF(D12<TODAY(),"Overdue","Open")) -> Overdue | K12: =IF(H12=0,0,MAX(0,TODAY()-D12)) -> 932 | L12: =IF(H12=0,"Paid",IF(K12<=30,"0-30 Days",IF(K12<=60,"31-60 Days",IF(K12<=90,"61-90 Days",IF(K12<=120,"91-120 Days","120+ Days"))))) -> 120+ Days | M12: 45292
A13: INV-100012 | B13: CUST-012 | C13: 45312 | D13: 45342 | E13: 45410 | F13: 44676.57 | G13: 44676.57 | H13: =MAX(0,F13-G13) -> 0 | I13: =IF(E13="","",MAX(0,E13-D13)) -> 68 | J13: =IF(H13=0,"Paid",IF(D13<TODAY(),"Overdue","Open")) -> Paid | K13: =IF(H13=0,0,MAX(0,TODAY()-D13)) -> 0 | L13: =IF(H13=0,"Paid",IF(K13<=30,"0-30 Days",IF(K13<=60,"31-60 Days",IF(K13<=90,"61-90 Days",IF(K13<=120,"91-120 Days","120+ Days"))))) -> Paid | M13: 45292 | N13: 45383
A14: INV-100013 | B14: CUST-020 | C14: 45301 | D14: 45331 | E14: 45382 | F14: 70154.75 | G14: 70154.75 | H14: =MAX(0,F14-G14) -> 0 | I14: =IF(E14="","",MAX(0,E14-D14)) -> 51 | J14: =IF(H14=0,"Paid",IF(D14<TODAY(),"Overdue","Open")) -> Paid | K14: =IF(H14=0,0,MAX(0,TODAY()-D14)) -> 0 | L14: =IF(H14=0,"Paid",IF(K14<=30,"0-30 Days",IF(K14<=60,"31-60 Days",IF(K14<=90,"61-90 Days",IF(K14<=120,"91-120 Days","120+ Days"))))) -> Paid | M14: 45292 | N14: 45352
A15: INV-100014 | B15: CUST-040 | C15: 45309 | D15: 45339 | F15: 42225.47 | G15: 0 | H15: =MAX(0,F15-G15) -> 42225.47 | I15: =IF(E15="","",MAX(0,E15-D15)) | J15: =IF(H15=0,"Paid",IF(D15<TODAY(),"Overdue","Open")) -> Overdue | K15: =IF(H15=0,0,MAX(0,TODAY()-D15)) -> 917 | L15: =IF(H15=0,"Paid",IF(K15<=30,"0-30 Days",IF(K15<=60,"31-60 Days",IF(K15<=90,"61-90 Days",IF(K15<=120,"91-120 Days","120+ Days"))))) -> 120+ Days | M15: 45292
A16: INV-100015 | B16: CUST-009 | C16: 45317 | D16: 45347 | E16: 45351 | F16: 94656.55 | G16: 94656.55 | H16: =MAX(0,F16-G16) -> 0 | I16: =IF(E16="","",MAX(0,E16-D16)) -> 4 | J16: =IF(H16=0,"Paid",IF(D16<TODAY(),"Overdue","Open")) -> Paid | K16: =IF(H16=0,0,MAX(0,TODAY()-D16)) -> 0 | L16: =IF(H16=0,"Paid",IF(K16<=30,"0-30 Days",IF(K16<=60,"31-60 Days",IF(K16<=90,"61-90 Days",IF(K16<=120,"91-120 Days","120+ Days"))))) -> Paid | M16: 45292 | N16: 45323
A17: INV-100016 | B17: CUST-041 | C17: 45298 | D17: 45328 | E17: 45328 | F17: 30922.74 | G17: 30922.74 | H17: =MAX(0,F17-G17) -> 0 | I17: =IF(E17="","",MAX(0,E17-D17)) -> 0 | J17: =IF(H17=0,"Paid",IF(D17<TODAY(),"Overdue","Open")) -> Paid | K17: =IF(H17=0,0,MAX(0,TODAY()-D17)) -> 0 | L17: =IF(H17=0,"Paid",IF(K17<=30,"0-30 Days",IF(K17<=60,"31-60 Days",IF(K17<=90,"61-90 Days",IF(K17<=120,"91-120 Days","120+ Days"))))) -> Paid | M17: 45292 | N17: 45323
A18: INV-100017 | B18: CUST-007 | C18: 45299 | D18: 45329 | F18: 54384.24 | G18: 0 | H18: =MAX(0,F18-G18) -> 54384.24 | I18: =IF(E18="","",MAX(0,E18-D18)) | J18: =IF(H18=0,"Paid",IF(D18<TODAY(),"Overdue","Open")) -> Overdue | K18: =IF(H18=0,0,MAX(0,TODAY()-D18)) -> 927 | L18: =IF(H18=0,"Paid",IF(K18<=30,"0-30 Days",IF(K18<=60,"31-60 Days",IF(K18<=90,"61-90 Days",IF(K18<=120,"91-120 Days","120+ Days"))))) -> 120+ Days | M18: 45292
A19: INV-100018 | B19: CUST-011 | C19: 45300 | D19: 45330 | E19: 45342 | F19: 38070.04 | G19: 38070.04 | H19: =MAX(0,F19-G19) -> 0 | I19: =IF(E19="","",MAX(0,E19-D19)) -> 12 | J19: =IF(H19=0,"Paid",IF(D19<TODAY(),"Overdue","Open")) -> Paid | K19: =IF(H19=0,0,MAX(0,TODAY()-D19)) -> 0 | L19: =IF(H19=0,"Paid",IF(K19<=30,"0-30 Days",IF(K19<=60,"31-60 Days",IF(K19<=90,"61-90 Days",IF(K19<=120,"91-120 Days","120+ Days"))))) -> Paid | M19: 45292 | N19: 45323
A20: INV-100019 | B20: CUST-036 | C20: 45296 | D20: 45326 | E20: 45326 | F20: 40127.68 | G20: 40127.68 | H20: =MAX(0,F20-G20) -> 0 | I20: =IF(E20="","",MAX(0,E20-D20)) -> 0 | J20: =IF(H20=0,"Paid",IF(D20<TODAY(),"Overdue","Open")) -> Paid | K20: =IF(H20=0,0,MAX(0,TODAY()-D20)) -> 0 | L20: =IF(H20=0,"Paid",IF(K20<=30,"0-30 Days",IF(K20<=60,"31-60 Days",IF(K20<=90,"61-90 Days",IF(K20<=120,"91-120 Days","120+ Days"))))) -> Paid | M20: 45292 | N20: 45323
A21: INV-100020 | B21: CUST-048 | C21: 45298 | D21: 45328 | E21: 45328 | F21: 37168.05 | G21: 37168.05 | H21: =MAX(0,F21-G21) -> 0 | I21: =IF(E21="","",MAX(0,E21-D21)) -> 0 | J21: =IF(H21=0,"Paid",IF(D21<TODAY(),"Overdue","Open")) -> Paid | K21: =IF(H21=0,0,MAX(0,TODAY()-D21)) -> 0 | L21: =IF(H21=0,"Paid",IF(K21<=30,"0-30 Days",IF(K21<=60,"31-60 Days",IF(K21<=90,"61-90 Days",IF(K21<=120,"91-120 Days","120+ Days"))))) -> Paid | M21: 45292 | N21: 45323
A22: INV-100021 | B22: CUST-011 | C22: 45303 | D22: 45333 | E22: 45333 | F22: 31768.55 | G22: 31768.55 | H22: =MAX(0,F22-G22) -> 0 | I22: =IF(E22="","",MAX(0,E22-D22)) -> 0 | J22: =IF(H22=0,"Paid",IF(D22<TODAY(),"Overdue","Open")) -> Paid | K22: =IF(H22=0,0,MAX(0,TODAY()-D22)) -> 0 | L22: =IF(H22=0,"Paid",IF(K22<=30,"0-30 Days",IF(K22<=60,"31-60 Days",IF(K22<=90,"61-90 Days",IF(K22<=120,"91-120 Days","120+ Days"))))) -> Paid | M22: 45292 | N22: 45323
A23: INV-100022 | B23: CUST-018 | C23: 45297 | D23: 45327 | E23: 45341 | F23: 38826.07 | G23: 38826.07 | H23: =MAX(0,F23-G23) -> 0 | I23: =IF(E23="","",MAX(0,E23-D23)) -> 14 | J23: =IF(H23=0,"Paid",IF(D23<TODAY(),"Overdue","Open")) -> Paid | K23: =IF(H23=0,0,MAX(0,TODAY()-D23)) -> 0 | L23: =IF(H23=0,"Paid",IF(K23<=30,"0-30 Days",IF(K23<=60,"31-60 Days",IF(K23<=90,"61-90 Days",IF(K23<=120,"91-120 Days","120+ Days"))))) -> Paid | M23: 45292 | N23: 45323
A24: INV-100023 | B24: CUST-056 | C24: 45294 | D24: 45324 | E24: 45360 | F24: 31881.46 | G24: 31881.46 | H24: =MAX(0,F24-G24) -> 0 | I24: =IF(E24="","",MAX(0,E24-D24)) -> 36 | J24: =IF(H24=0,"Paid",IF(D24<TODAY(),"Overdue","Open")) -> Paid | K24: =IF(H24=0,0,MAX(0,TODAY()-D24)) -> 0 | L24: =IF(H24=0,"Paid",IF(K24<=30,"0-30 Days",IF(K24<=60,"31-60 Days",IF(K24<=90,"61-90 Days",IF(K24<=120,"91-120 Days","120+ Days"))))) -> Paid | M24: 45292 | N24: 45352
A25: INV-100024 | B25: CUST-060 | C25: 45302 | D25: 45332 | E25: 45332 | F25: 79663.67 | G25: 79663.67 | H25: =MAX(0,F25-G25) -> 0 | I25: =IF(E25="","",MAX(0,E25-D25)) -> 0 | J25: =IF(H25=0,"Paid",IF(D25<TODAY(),"Overdue","Open")) -> Paid | K25: =IF(H25=0,0,MAX(0,TODAY()-D25)) -> 0 | L25: =IF(H25=0,"Paid",IF(K25<=30,"0-30 Days",IF(K25<=60,"31-60 Days",IF(K25<=90,"61-90 Days",IF(K25<=120,"91-120 Days","120+ Days"))))) -> Paid | M25: 45292 | N25: 45323
A26: INV-100025 | B26: CUST-035 | C26: 45305 | D26: 45335 | E26: 45335 | F26: 43624.46 | G26: 43624.46 | H26: =MAX(0,F26-G26) -> 0 | I26: =IF(E26="","",MAX(0,E26-D26)) -> 0 | J26: =IF(H26=0,"Paid",IF(D26<TODAY(),"Overdue","Open")) -> Paid | K26: =IF(H26=0,0,MAX(0,TODAY()-D26)) -> 0 | L26: =IF(H26=0,"Paid",IF(K26<=30,"0-30 Days",IF(K26<=60,"31-60 Days",IF(K26<=90,"61-90 Days",IF(K26<=120,"91-120 Days","120+ Days"))))) -> Paid | M26: 45292 | N26: 45323
A27: INV-100026 | B27: CUST-027 | C27: 45292 | D27: 45322 | E27: 45366 | F27: 40125.58 | G27: 40125.58 | H27: =MAX(0,F27-G27) -> 0 | I27: =IF(E27="","",MAX(0,E27-D27)) -> 44 | J27: =IF(H27=0,"Paid",IF(D27<TODAY(),"Overdue","Open")) -> Paid | K27: =IF(H27=0,0,MAX(0,TODAY()-D27)) -> 0 | L27: =IF(H27=0,"Paid",IF(K27<=30,"0-30 Days",IF(K27<=60,"31-60 Days",IF(K27<=90,"61-90 Days",IF(K27<=120,"91-120 Days","120+ Days"))))) -> Paid | M27: 45292 | N27: 45352
A28: INV-100027 | B28: CUST-021 | C28: 45296 | D28: 45326 | F28: 23878.08 | G28: 0 | H28: =MAX(0,F28-G28) -> 23878.08 | I28: =IF(E28="","",MAX(0,E28-D28)) | J28: =IF(H28=0,"Paid",IF(D28<TODAY(),"Overdue","Open")) -> Overdue | K28: =IF(H28=0,0,MAX(0,TODAY()-D28)) -> 930 | L28: =IF(H28=0,"Paid",IF(K28<=30,"0-30 Days",IF(K28<=60,"31-60 Days",IF(K28<=90,"61-90 Days",IF(K28<=120,"91-120 Days","120+ Days"))))) -> 120+ Days | M28: 45292
A29: INV-100028 | B29: CUST-037 | C29: 45308 | D29: 45338 | E29: 45349 | F29: 17070.5 | G29: 17070.5 | H29: =MAX(0,F29-G29) -> 0 | I29: =IF(E29="","",MAX(0,E29-D29)) -> 11 | J29: =IF(H29=0,"Paid",IF(D29<TODAY(),"Overdue","Open")) -> Paid | K29: =IF(H29=0,0,MAX(0,TODAY()-D29)) -> 0 | L29: =IF(H29=0,"Paid",IF(K29<=30,"0-30 Days",IF(K29<=60,"31-60 Days",IF(K29<=90,"61-90 Days",IF(K29<=120,"91-120 Days","120+ Days"))))) -> Paid | M29: 45292 | N29: 45323
A30: INV-100029 | B30: CUST-036 | C30: 45309 | D30: 45339 | E30: 45354 | F30: 25565.62 | G30: 18829.02 | H30: =MAX(0,F30-G30) -> 6736.6 | I30: =IF(E30="","",MAX(0,E30-D30)) -> 15 | J30: =IF(H30=0,"Paid",IF(D30<TODAY(),"Overdue","Open")) -> Overdue | K30: =IF(H30=0,0,MAX(0,TODAY()-D30)) -> 917 | L30: =IF(H30=0,"Paid",IF(K30<=30,"0-30 Days",IF(K30<=60,"31-60 Days",IF(K30<=90,"61-90 Days",IF(K30<=120,"91-120 Days","120+ Days"))))) -> 120+ Days | M30: 45292 | N30: 45352
A31: INV-100030 | B31: CUST-018 | C31: 45294 | D31: 45324 | E31: 45324 | F31: 34910.18 | G31: 34910.18 | H31: =MAX(0,F31-G31) -> 0 | I31: =IF(E31="","",MAX(0,E31-D31)) -> 0 | J31: =IF(H31=0,"Paid",IF(D31<TODAY(),"Overdue","Open")) -> Paid | K31: =IF(H31=0,0,MAX(0,TODAY()-D31)) -> 0 | L31: =IF(H31=0,"Paid",IF(K31<=30,"0-30 Days",IF(K31<=60,"31-60 Days",IF(K31<=90,"61-90 Days",IF(K31<=120,"91-120 Days","120+ Days"))))) -> Paid | M31: 45292 | N31: 45323
A32: INV-100031 | B32: CUST-002 | C32: 45295 | D32: 45325 | E32: 45325 | F32: 70836.06 | G32: 70836.06 | H32: =MAX(0,F32-G32) -> 0 | I32: =IF(E32="","",MAX(0,E32-D32)) -> 0 | J32: =IF(H32=0,"Paid",IF(D32<TODAY(),"Overdue","Open")) -> Paid | K32: =IF(H32=0,0,MAX(0,TODAY()-D32)) -> 0 | L32: =IF(H32=0,"Paid",IF(K32<=30,"0-30 Days",IF(K32<=60,"31-60 Days",IF(K32<=90,"61-90 Days",IF(K32<=120,"91-120 Days","120+ Days"))))) -> Paid | M32: 45292 | N32: 45323
A33: INV-100032 | B33: CUST-010 | C33: 45302 | D33: 45332 | E33: 45332 | F33: 17036.7 | G33: 17036.7 | H33: =MAX(0,F33-G33) -> 0 | I33: =IF(E33="","",MAX(0,E33-D33)) -> 0 | J33: =IF(H33=0,"Paid",IF(D33<TODAY(),"Overdue","Open")) -> Paid | K33: =IF(H33=0,0,MAX(0,TODAY()-D33)) -> 0 | L33: =IF(H33=0,"Paid",IF(K33<=30,"0-30 Days",IF(K33<=60,"31-60 Days",IF(K33<=90,"61-90 Days",IF(K33<=120,"91-120 Days","120+ Days"))))) -> Paid | M33: 45292 | N33: 45323
A34: INV-100033 | B34: CUST-058 | C34: 45318 | D34: 45348 | E34: 45348 | F34: 104851.72 | G34: 104851.72 | H34: =MAX(0,F34-G34) -> 0 | I34: =IF(E34="","",MAX(0,E34-D34)) -> 0 | J34: =IF(H34=0,"Paid",IF(D34<TODAY(),"Overdue","Open")) -> Paid | K34: =IF(H34=0,0,MAX(0,TODAY()-D34)) -> 0 | L34: =IF(H34=0,"Paid",IF(K34<=30,"0-30 Days",IF(K34<=60,"31-60 Days",IF(K34<=90,"61-90 Days",IF(K34<=120,"91-120 Days","120+ Days"))))) -> Paid | M34: 45292 | N34: 45323
A35: INV-100034 | B35: CUST-026 | C35: 45312 | D35: 45342 | E35: 45351 | F35: 31177.85 | G35: 15147.69 | H35: =MAX(0,F35-G35) -> 16030.16 | I35: =IF(E35="","",MAX(0,E35-D35)) -> 9 | J35: =IF(H35=0,"Paid",IF(D35<TODAY(),"Overdue","Open")) -> Overdue | K35: =IF(H35=0,0,MAX(0,TODAY()-D35)) -> 914 | L35: =IF(H35=0,"Paid",IF(K35<=30,"0-30 Days",IF(K35<=60,"31-60 Days",IF(K35<=90,"61-90 Days",IF(K35<=120,"91-120 Days","120+ Days"))))) -> 120+ Days | M35: 45292 | N35: 45323
A36: INV-100035 | B36: CUST-029 | C36: 45300 | D36: 45330 | F36: 33359.48 | G36: 0 | H36: =MAX(0,F36-G36) -> 33359.48 | I36: =IF(E36="","",MAX(0,E36-D36)) | J36: =IF(H36=0,"Paid",IF(D36<TODAY(),"Overdue","Open")) -> Overdue | K36: =IF(H36=0,0,MAX(0,TODAY()-D36)) -> 926 | L36: =IF(H36=0,"Paid",IF(K36<=30,"0-30 Days",IF(K36<=60,"31-60 Days",IF(K36<=90,"61-90 Days",IF(K36<=120,"91-120 Days","120+ Days"))))) -> 120+ Days | M36: 45292
A37: INV-100036 | B37: CUST-029 | C37: 45300 | D37: 45330 | E37: 45334 | F37: 48490.41 | G37: 48490.41 | H37: =MAX(0,F37-G37) -> 0 | I37: =IF(E37="","",MAX(0,E37-D37)) -> 4 | J37: =IF(H37=0,"Paid",IF(D37<TODAY(),"Overdue","Open")) -> Paid | K37: =IF(H37=0,0,MAX(0,TODAY()-D37)) -> 0 | L37: =IF(H37=0,"Paid",IF(K37<=30,"0-30 Days",IF(K37<=60,"31-60 Days",IF(K37<=90,"61-90 Days",IF(K37<=120,"91-120 Days","120+ Days"))))) -> Paid | M37: 45292 | N37: 45323
A38: INV-100037 | B38: CUST-047 | C38: 45304 | D38: 45334 | E38: 45408 | F38: 33490.08 | G38: 25785.26 | H38: =MAX(0,F38-G38) -> 7704.82 | I38: =IF(E38="","",MAX(0,E38-D38)) -> 74 | J38: =IF(H38=0,"Paid",IF(D38<TODAY(),"Overdue","Open")) -> Overdue | K38: =IF(H38=0,0,MAX(0,TODAY()-D38)) -> 922 | L38: =IF(H38=0,"Paid",IF(K38<=30,"0-30 Days",IF(K38<=60,"31-60 Days",IF(K38<=90,"61-90 Days",IF(K38<=120,"91-120 Days","120+ Days"))))) -> 120+ Days | M38: 45292 | N38: 45383
A39: INV-100038 | B39: CUST-004 | C39: 45295 | D39: 45325 | E39: 45368 | F39: 28129.38 | G39: 28129.38 | H39: =MAX(0,F39-G39) -> 0 | I39: =IF(E39="","",MAX(0,E39-D39)) -> 43 | J39: =IF(H39=0,"Paid",IF(D39<TODAY(),"Overdue","Open")) -> Paid | K39: =IF(H39=0,0,MAX(0,TODAY()-D39)) -> 0 | L39: =IF(H39=0,"Paid",IF(K39<=30,"0-30 Days",IF(K39<=60,"31-60 Days",IF(K39<=90,"61-90 Days",IF(K39<=120,"91-120 Days","120+ Days"))))) -> Paid | M39: 45292 | N39: 45352
A40: INV-100039 | B40: CUST-005 | C40: 45313 | D40: 45343 | E40: 45350 | F40: 46326.34 | G40: 46326.34 | H40: =MAX(0,F40-G40) -> 0 | I40: =IF(E40="","",MAX(0,E40-D40)) -> 7 | J40: =IF(H40=0,"Paid",IF(D40<TODAY(),"Overdue","Open")) -> Paid | K40: =IF(H40=0,0,MAX(0,TODAY()-D40)) -> 0 | L40: =IF(H40=0,"Paid",IF(K40<=30,"0-30 Days",IF(K40<=60,"31-60 Days",IF(K40<=90,"61-90 Days",IF(K40<=120,"91-120 Days","120+ Days"))))) -> Paid | M40: 45292 | N40: 45323
A41: INV-100040 | B41: CUST-017 | C41: 45302 | D41: 45332 | E41: 45337 | F41: 25671.66 | G41: 25671.66 | H41: =MAX(0,F41-G41) -> 0 | I41: =IF(E41="","",MAX(0,E41-D41)) -> 5 | J41: =IF(H41=0,"Paid",IF(D41<TODAY(),"Overdue","Open")) -> Paid | K41: =IF(H41=0,0,MAX(0,TODAY()-D41)) -> 0 | L41: =IF(H41=0,"Paid",IF(K41<=30,"0-30 Days",IF(K41<=60,"31-60 Days",IF(K41<=90,"61-90 Days",IF(K41<=120,"91-120 Days","120+ Days"))))) -> Paid | M41: 45292 | N41: 45323
A42: INV-100041 | B42: CUST-030 | C42: 45298 | D42: 45328 | E42: 45344 | F42: 90702.95 | G42: 90702.95 | H42: =MAX(0,F42-G42) -> 0 | I42: =IF(E42="","",MAX(0,E42-D42)) -> 16 | J42: =IF(H42=0,"Paid",IF(D42<TODAY(),"Overdue","Open")) -> Paid | K42: =IF(H42=0,0,MAX(0,TODAY()-D42)) -> 0 | L42: =IF(H42=0,"Paid",IF(K42<=30,"0-30 Days",IF(K42<=60,"31-60 Days",IF(K42<=90,"61-90 Days",IF(K42<=120,"91-120 Days","120+ Days"))))) -> Paid | M42: 45292 | N42: 45323
A43: INV-100042 | B43: CUST-041 | C43: 45298 | D43: 45328 | E43: 45338 | F43: 20705.89 | G43: 20705.89 | H43: =MAX(0,F43-G43) -> 0 | I43: =IF(E43="","",MAX(0,E43-D43)) -> 10 | J43: =IF(H43=0,"Paid",IF(D43<TODAY(),"Overdue","Open")) -> Paid | K43: =IF(H43=0,0,MAX(0,TODAY()-D43)) -> 0 | L43: =IF(H43=0,"Paid",IF(K43<=30,"0-30 Days",IF(K43<=60,"31-60 Days",IF(K43<=90,"61-90 Days",IF(K43<=120,"91-120 Days","120+ Days"))))) -> Paid | M43: 45292 | N43: 45323
A44: INV-100043 | B44: CUST-030 | C44: 45302 | D44: 45332 | F44: 14624.85 | G44: 0 | H44: =MAX(0,F44-G44) -> 14624.85 | I44: =IF(E44="","",MAX(0,E44-D44)) | J44: =IF(H44=0,"Paid",IF(D44<TODAY(),"Overdue","Open")) -> Overdue | K44: =IF(H44=0,0,MAX(0,TODAY()-D44)) -> 924 | L44: =IF(H44=0,"Paid",IF(K44<=30,"0-30 Days",IF(K44<=60,"31-60 Days",IF(K44<=90,"61-90 Days",IF(K44<=120,"91-120 Days","120+ Days"))))) -> 120+ Days | M44: 45292
A45: INV-100044 | B45: CUST-027 | C45: 45316 | D45: 45346 | F45: 49017.43 | G45: 0 | H45: =MAX(0,F45-G45) -> 49017.43 | I45: =IF(E45="","",MAX(0,E45-D45)) | J45: =IF(H45=0,"Paid",IF(D45<TODAY(),"Overdue","Open")) -> Overdue | K45: =IF(H45=0,0,MAX(0,TODAY()-D45)) -> 910 | L45: =IF(H45=0,"Paid",IF(K45<=30,"0-30 Days",IF(K45<=60,"31-60 Days",IF(K45<=90,"61-90 Days",IF(K45<=120,"91-120 Days","120+ Days"))))) -> 120+ Days | M45: 45292
A46: INV-100045 | B46: CUST-057 | C46: 45300 | D46: 45330 | E46: 45332 | F46: 44136.59 | G46: 44136.59 | H46: =MAX(0,F46-G46) -> 0 | I46: =IF(E46="","",MAX(0,E46-D46)) -> 2 | J46: =IF(H46=0,"Paid",IF(D46<TODAY(),"Overdue","Open")) -> Paid | K46: =IF(H46=0,0,MAX(0,TODAY()-D46)) -> 0 | L46: =IF(H46=0,"Paid",IF(K46<=30,"0-30 Days",IF(K46<=60,"31-60 Days",IF(K46<=90,"61-90 Days",IF(K46<=120,"91-120 Days","120+ Days"))))) -> Paid | M46: 45292 | N46: 45323
A47: INV-100046 | B47: CUST-010 | C47: 45313 | D47: 45343 | E47: 45352 | F47: 36065.12 | G47: 36065.12 | H47: =MAX(0,F47-G47) -> 0 | I47: =IF(E47="","",MAX(0,E47-D47)) -> 9 | J47: =IF(H47=0,"Paid",IF(D47<TODAY(),"Overdue","Open")) -> Paid | K47: =IF(H47=0,0,MAX(0,TODAY()-D47)) -> 0 | L47: =IF(H47=0,"Paid",IF(K47<=30,"0-30 Days",IF(K47<=60,"31-60 Days",IF(K47<=90,"61-90 Days",IF(K47<=120,"91-120 Days","120+ Days"))))) -> Paid | M47: 45292 | N47: 45352
A48: INV-100047 | B48: CUST-035 | C48: 45318 | D48: 45348 | E48: 45357 | F48: 9305.29 | G48: 9305.29 | H48: =MAX(0,F48-G48) -> 0 | I48: =IF(E48="","",MAX(0,E48-D48)) -> 9 | J48: =IF(H48=0,"Paid",IF(D48<TODAY(),"Overdue","Open")) -> Paid | K48: =IF(H48=0,0,MAX(0,TODAY()-D48)) -> 0 | L48: =IF(H48=0,"Paid",IF(K48<=30,"0-30 Days",IF(K48<=60,"31-60 Days",IF(K48<=90,"61-90 Days",IF(K48<=120,"91-120 Days","120+ Days"))))) -> Paid | M48: 45292 | N48: 45352
A49: INV-100048 | B49: CUST-033 | C49: 45315 | D49: 45345 | E49: 45345 | F49: 44927.11 | G49: 44927.11 | H49: =MAX(0,F49-G49) -> 0 | I49: =IF(E49="","",MAX(0,E49-D49)) -> 0 | J49: =IF(H49=0,"Paid",IF(D49<TODAY(),"Overdue","Open")) -> Paid | K49: =IF(H49=0,0,MAX(0,TODAY()-D49)) -> 0 | L49: =IF(H49=0,"Paid",IF(K49<=30,"0-30 Days",IF(K49<=60,"31-60 Days",IF(K49<=90,"61-90 Days",IF(K49<=120,"91-120 Days","120+ Days"))))) -> Paid | M49: 45292 | N49: 45323
A50: INV-100049 | B50: CUST-029 | C50: 45296 | D50: 45326 | E50: 45345 | F50: 98719.98 | G50: 98719.98 | H50: =MAX(0,F50-G50) -> 0 | I50: =IF(E50="","",MAX(0,E50-D50)) -> 19 | J50: =IF(H50=0,"Paid",IF(D50<TODAY(),"Overdue","Open")) -> Paid | K50: =IF(H50=0,0,MAX(0,TODAY()-D50)) -> 0 | L50: =IF(H50=0,"Paid",IF(K50<=30,"0-30 Days",IF(K50<=60,"31-60 Days",IF(K50<=90,"61-90 Days",IF(K50<=120,"91-120 Days","120+ Days"))))) -> Paid | M50: 45292 | N50: 45323
A51: INV-100050 | B51: CUST-049 | C51: 45303 | D51: 45333 | E51: 45345 | F51: 31866.52 | G51: 31866.52 | H51: =MAX(0,F51-G51) -> 0 | I51: =IF(E51="","",MAX(0,E51-D51)) -> 12 | J51: =IF(H51=0,"Paid",IF(D51<TODAY(),"Overdue","Open")) -> Paid | K51: =IF(H51=0,0,MAX(0,TODAY()-D51)) -> 0 | L51: =IF(H51=0,"Paid",IF(K51<=30,"0-30 Days",IF(K51<=60,"31-60 Days",IF(K51<=90,"61-90 Days",IF(K51<=120,"91-120 Days","120+ Days"))))) -> Paid | M51: 45292 | N51: 45323
A52: INV-100051 | B52: CUST-017 | C52: 45298 | D52: 45328 | F52: 78043.73 | G52: 0 | H52: =MAX(0,F52-G52) -> 78043.73 | I52: =IF(E52="","",MAX(0,E52-D52)) | J52: =IF(H52=0,"Paid",IF(D52<TODAY(),"Overdue","Open")) -> Overdue | K52: =IF(H52=0,0,MAX(0,TODAY()-D52)) -> 928 | L52: =IF(H52=0,"Paid",IF(K52<=30,"0-30 Days",IF(K52<=60,"31-60 Days",IF(K52<=90,"61-90 Days",IF(K52<=120,"91-120 Days","120+ Days"))))) -> 120+ Days | M52: 45292
A53: INV-100052 | B53: CUST-058 | C53: 45300 | D53: 45330 | E53: 45343 | F53: 98989.73 | G53: 98989.73 | H53: =MAX(0,F53-G53) -> 0 | I53: =IF(E53="","",MAX(0,E53-D53)) -> 13 | J53: =IF(H53=0,"Paid",IF(D53<TODAY(),"Overdue","Open")) -> Paid | K53: =IF(H53=0,0,MAX(0,TODAY()-D53)) -> 0 | L53: =IF(H53=0,"Paid",IF(K53<=30,"0-30 Days",IF(K53<=60,"31-60 Days",IF(K53<=90,"61-90 Days",IF(K53<=120,"91-120 Days","120+ Days"))))) -> Paid | M53: 45292 | N53: 45323
A54: INV-100053 | B54: CUST-020 | C54: 45317 | D54: 45347 | F54: 48603.28 | G54: 0 | H54: =MAX(0,F54-G54) -> 48603.28 | I54: =IF(E54="","",MAX(0,E54-D54)) | J54: =IF(H54=0,"Paid",IF(D54<TODAY(),"Overdue","Open")) -> Overdue | K54: =IF(H54=0,0,MAX(0,TODAY()-D54)) -> 909 | L54: =IF(H54=0,"Paid",IF(K54<=30,"0-30 Days",IF(K54<=60,"31-60 Days",IF(K54<=90,"61-90 Days",IF(K54<=120,"91-120 Days","120+ Days"))))) -> 120+ Days | M54: 45292
A55: INV-100054 | B55: CUST-033 | C55: 45314 | D55: 45344 | E55: 45344 | F55: 32431.52 | G55: 32431.52 | H55: =MAX(0,F55-G55) -> 0 | I55: =IF(E55="","",MAX(0,E55-D55)) -> 0 | J55: =IF(H55=0,"Paid",IF(D55<TODAY(),"Overdue","Open")) -> Paid | K55: =IF(H55=0,0,MAX(0,TODAY()-D55)) -> 0 | L55: =IF(H55=0,"Paid",IF(K55<=30,"0-30 Days",IF(K55<=60,"31-60 Days",IF(K55<=90,"61-90 Days",IF(K55<=120,"91-120 Days","120+ Days"))))) -> Paid | M55: 45292 | N55: 45323
A56: INV-100055 | B56: CUST-032 | C56: 45296 | D56: 45326 | F56: 19968.93 | G56: 0 | H56: =MAX(0,F56-G56) -> 19968.93 | I56: =IF(E56="","",MAX(0,E56-D56)) | J56: =IF(H56=0,"Paid",IF(D56<TODAY(),"Overdue","Open")) -> Overdue | K56: =IF(H56=0,0,MAX(0,TODAY()-D56)) -> 930 | L56: =IF(H56=0,"Paid",IF(K56<=30,"0-30 Days",IF(K56<=60,"31-60 Days",IF(K56<=90,"61-90 Days",IF(K56<=120,"91-120 Days","120+ Days"))))) -> 120+ Days | M56: 45292
A57: INV-100056 | B57: CUST-051 | C57: 45311 | D57: 45341 | E57: 45359 | F57: 34376.96 | G57: 34376.96 | H57: =MAX(0,F57-G57) -> 0 | I57: =IF(E57="","",MAX(0,E57-D57)) -> 18 | J57: =IF(H57=0,"Paid",IF(D57<TODAY(),"Overdue","Open")) -> Paid | K57: =IF(H57=0,0,MAX(0,TODAY()-D57)) -> 0 | L57: =IF(H57=0,"Paid",IF(K57<=30,"0-30 Days",IF(K57<=60,"31-60 Days",IF(K57<=90,"61-90 Days",IF(K57<=120,"91-120 Days","120+ Days"))))) -> Paid | M57: 45292 | N57: 45352
A58: INV-100057 | B58: CUST-027 | C58: 45308 | D58: 45338 | F58: 57063.85 | G58: 0 | H58: =MAX(0,F58-G58) -> 57063.85 | I58: =IF(E58="","",MAX(0,E58-D58)) | J58: =IF(H58=0,"Paid",IF(D58<TODAY(),"Overdue","Open")) -> Overdue | K58: =IF(H58=0,0,MAX(0,TODAY()-D58)) -> 918 | L58: =IF(H58=0,"Paid",IF(K58<=30,"0-30 Days",IF(K58<=60,"31-60 Days",IF(K58<=90,"61-90 Days",IF(K58<=120,"91-120 Days","120+ Days"))))) -> 120+ Days | M58: 45292
A59: INV-100058 | B59: CUST-018 | C59: 45311 | D59: 45341 | F59: 36797.15 | G59: 0 | H59: =MAX(0,F59-G59) -> 36797.15 | I59: =IF(E59="","",MAX(0,E59-D59)) | J59: =IF(H59=0,"Paid",IF(D59<TODAY(),"Overdue","Open")) -> Overdue | K59: =IF(H59=0,0,MAX(0,TODAY()-D59)) -> 915 | L59: =IF(H59=0,"Paid",IF(K59<=30,"0-30 Days",IF(K59<=60,"31-60 Days",IF(K59<=90,"61-90 Days",IF(K59<=120,"91-120 Days","120+ Days"))))) -> 120+ Days | M59: 45292
A60: INV-100059 | B60: CUST-002 | C60: 45296 | D60: 45326 | E60: 45326 | F60: 87656.03 | G60: 87656.03 | H60: =MAX(0,F60-G60) -> 0 | I60: =IF(E60="","",MAX(0,E60-D60)) -> 0 | J60: =IF(H60=0,"Paid",IF(D60<TODAY(),"Overdue","Open")) -> Paid | K60: =IF(H60=0,0,MAX(0,TODAY()-D60)) -> 0 | L60: =IF(H60=0,"Paid",IF(K60<=30,"0-30 Days",IF(K60<=60,"31-60 Days",IF(K60<=90,"61-90 Days",IF(K60<=120,"91-120 Days","120+ Days"))))) -> Paid | M60: 45292 | N60: 45323
A61: INV-100060 | B61: CUST-056 | C61: 45349 | D61: 45379 | F61: 61159.27 | G61: 0 | H61: =MAX(0,F61-G61) -> 61159.27 | I61: =IF(E61="","",MAX(0,E61-D61)) | J61: =IF(H61=0,"Paid",IF(D61<TODAY(),"Overdue","Open")) -> Overdue | K61: =IF(H61=0,0,MAX(0,TODAY()-D61)) -> 877 | L61: =IF(H61=0,"Paid",IF(K61<=30,"0-30 Days",IF(K61<=60,"31-60 Days",IF(K61<=90,"61-90 Days",IF(K61<=120,"91-120 Days","120+ Days"))))) -> 120+ Days | M61: 45323
A62: INV-100061 | B62: CUST-057 | C62: 45334 | D62: 45364 | E62: 45364 | F62: 137339.22 | G62: 137339.22 | H62: =MAX(0,F62-G62) -> 0 | I62: =IF(E62="","",MAX(0,E62-D62)) -> 0 | J62: =IF(H62=0,"Paid",IF(D62<TODAY(),"Overdue","Open")) -> Paid | K62: =IF(H62=0,0,MAX(0,TODAY()-D62)) -> 0 | L62: =IF(H62=0,"Paid",IF(K62<=30,"0-30 Days",IF(K62<=60,"31-60 Days",IF(K62<=90,"61-90 Days",IF(K62<=120,"91-120 Days","120+ Days"))))) -> Paid | M62: 45323 | N62: 45352
A63: INV-100062 | B63: CUST-006 | C63: 45326 | D63: 45356 | F63: 92257.6 | G63: 0 | H63: =MAX(0,F63-G63) -> 92257.6 | I63: =IF(E63="","",MAX(0,E63-D63)) | J63: =IF(H63=0,"Paid",IF(D63<TODAY(),"Overdue","Open")) -> Overdue | K63: =IF(H63=0,0,MAX(0,TODAY()-D63)) -> 900 | L63: =IF(H63=0,"Paid",IF(K63<=30,"0-30 Days",IF(K63<=60,"31-60 Days",IF(K63<=90,"61-90 Days",IF(K63<=120,"91-120 Days","120+ Days"))))) -> 120+ Days | M63: 45323
A64: INV-100063 | B64: CUST-016 | C64: 45337 | D64: 45367 | E64: 45367 | F64: 78452.83 | G64: 78452.83 | H64: =MAX(0,F64-G64) -> 0 | I64: =IF(E64="","",MAX(0,E64-D64)) -> 0 | J64: =IF(H64=0,"Paid",IF(D64<TODAY(),"Overdue","Open")) -> Paid | K64: =IF(H64=0,0,MAX(0,TODAY()-D64)) -> 0 | L64: =IF(H64=0,"Paid",IF(K64<=30,"0-30 Days",IF(K64<=60,"31-60 Days",IF(K64<=90,"61-90 Days",IF(K64<=120,"91-120 Days","120+ Days"))))) -> Paid | M64: 45323 | N64: 45352
A65: INV-100064 | B65: CUST-044 | C65: 45323 | D65: 45353 | E65: 45366 | F65: 15824.22 | G65: 15824.22 | H65: =MAX(0,F65-G65) -> 0 | I65: =IF(E65="","",MAX(0,E65-D65)) -> 13 | J65: =IF(H65=0,"Paid",IF(D65<TODAY(),"Overdue","Open")) -> Paid | K65: =IF(H65=0,0,MAX(0,TODAY()-D65)) -> 0 | L65: =IF(H65=0,"Paid",IF(K65<=30,"0-30 Days",IF(K65<=60,"31-60 Days",IF(K65<=90,"61-90 Days",IF(K65<=120,"91-120 Days","120+ Days"))))) -> Paid | M65: 45323 | N65: 45352
A66: INV-100065 | B66: CUST-036 | C66: 45336 | D66: 45366 | E66: 45366 | F66: 44442.47 | G66: 44442.47 | H66: =MAX(0,F66-G66) -> 0 | I66: =IF(E66="","",MAX(0,E66-D66)) -> 0 | J66: =IF(H66=0,"Paid",IF(D66<TODAY(),"Overdue","Open")) -> Paid | K66: =IF(H66=0,0,MAX(0,TODAY()-D66)) -> 0 | L66: =IF(H66=0,"Paid",IF(K66<=30,"0-30 Days",IF(K66<=60,"31-60 Days",IF(K66<=90,"61-90 Days",IF(K66<=120,"91-120 Days","120+ Days"))))) -> Paid | M66: 45323 | N66: 45352
A67: INV-100066 | B67: CUST-004 | C67: 45347 | D67: 45377 | E67: 45411 | F67: 39335.96 | G67: 39335.96 | H67: =MAX(0,F67-G67) -> 0 | I67: =IF(E67="","",MAX(0,E67-D67)) -> 34 | J67: =IF(H67=0,"Paid",IF(D67<TODAY(),"Overdue","Open")) -> Paid | K67: =IF(H67=0,0,MAX(0,TODAY()-D67)) -> 0 | L67: =IF(H67=0,"Paid",IF(K67<=30,"0-30 Days",IF(K67<=60,"31-60 Days",IF(K67<=90,"61-90 Days",IF(K67<=120,"91-120 Days","120+ Days"))))) -> Paid | M67: 45323 | N67: 45383
A68: INV-100067 | B68: CUST-006 | C68: 45324 | D68: 45354 | E68: 45422 | F68: 41193.38 | G68: 41193.38 | H68: =MAX(0,F68-G68) -> 0 | I68: =IF(E68="","",MAX(0,E68-D68)) -> 68 | J68: =IF(H68=0,"Paid",IF(D68<TODAY(),"Overdue","Open")) -> Paid | K68: =IF(H68=0,0,MAX(0,TODAY()-D68)) -> 0 | L68: =IF(H68=0,"Paid",IF(K68<=30,"0-30 Days",IF(K68<=60,"31-60 Days",IF(K68<=90,"61-90 Days",IF(K68<=120,"91-120 Days","120+ Days"))))) -> Paid | M68: 45323 | N68: 45413
A69: INV-100068 | B69: CUST-032 | C69: 45325 | D69: 45355 | E69: 45417 | F69: 51099.79 | G69: 51099.79 | H69: =MAX(0,F69-G69) -> 0 | I69: =IF(E69="","",MAX(0,E69-D69)) -> 62 | J69: =IF(H69=0,"Paid",IF(D69<TODAY(),"Overdue","Open")) -> Paid | K69: =IF(H69=0,0,MAX(0,TODAY()-D69)) -> 0 | L69: =IF(H69=0,"Paid",IF(K69<=30,"0-30 Days",IF(K69<=60,"31-60 Days",IF(K69<=90,"61-90 Days",IF(K69<=120,"91-120 Days","120+ Days"))))) -> Paid | M69: 45323 | N69: 45413
A70: INV-100069 | B70: CUST-037 | C70: 45346 | D70: 45376 | F70: 59951.47 | G70: 0 | H70: =MAX(0,F70-G70) -> 59951.47 | I70: =IF(E70="","",MAX(0,E70-D70)) | J70: =IF(H70=0,"Paid",IF(D70<TODAY(),"Overdue","Open")) -> Overdue | K70: =IF(H70=0,0,MAX(0,TODAY()-D70)) -> 880 | L70: =IF(H70=0,"Paid",IF(K70<=30,"0-30 Days",IF(K70<=60,"31-60 Days",IF(K70<=90,"61-90 Days",IF(K70<=120,"91-120 Days","120+ Days"))))) -> 120+ Days | M70: 45323
A71: INV-100070 | B71: CUST-011 | C71: 45343 | D71: 45373 | E71: 45378 | F71: 50850.34 | G71: 50850.34 | H71: =MAX(0,F71-G71) -> 0 | I71: =IF(E71="","",MAX(0,E71-D71)) -> 5 | J71: =IF(H71=0,"Paid",IF(D71<TODAY(),"Overdue","Open")) -> Paid | K71: =IF(H71=0,0,MAX(0,TODAY()-D71)) -> 0 | L71: =IF(H71=0,"Paid",IF(K71<=30,"0-30 Days",IF(K71<=60,"31-60 Days",IF(K71<=90,"61-90 Days",IF(K71<=120,"91-120 Days","120+ Days"))))) -> Paid | M71: 45323 | N71: 45352
A72: INV-100071 | B72: CUST-011 | C72: 45327 | D72: 45357 | E72: 45357 | F72: 12756.76 | G72: 12756.76 | H72: =MAX(0,F72-G72) -> 0 | I72: =IF(E72="","",MAX(0,E72-D72)) -> 0 | J72: =IF(H72=0,"Paid",IF(D72<TODAY(),"Overdue","Open")) -> Paid | K72: =IF(H72=0,0,MAX(0,TODAY()-D72)) -> 0 | L72: =IF(H72=0,"Paid",IF(K72<=30,"0-30 Days",IF(K72<=60,"31-60 Days",IF(K72<=90,"61-90 Days",IF(K72<=120,"91-120 Days","120+ Days"))))) -> Paid | M72: 45323 | N72: 45352
A73: INV-100072 | B73: CUST-008 | C73: 45324 | D73: 45354 | E73: 45393 | F73: 10577.78 | G73: 10577.78 | H73: =MAX(0,F73-G73) -> 0 | I73: =IF(E73="","",MAX(0,E73-D73)) -> 39 | J73: =IF(H73=0,"Paid",IF(D73<TODAY(),"Overdue","Open")) -> Paid | K73: =IF(H73=0,0,MAX(0,TODAY()-D73)) -> 0 | L73: =IF(H73=0,"Paid",IF(K73<=30,"0-30 Days",IF(K73<=60,"31-60 Days",IF(K73<=90,"61-90 Days",IF(K73<=120,"91-120 Days","120+ Days"))))) -> Paid | M73: 45323 | N73: 45383
A74: INV-100073 | B74: CUST-034 | C74: 45349 | D74: 45379 | E74: 45405 | F74: 42564.87 | G74: 42564.87 | H74: =MAX(0,F74-G74) -> 0 | I74: =IF(E74="","",MAX(0,E74-D74)) -> 26 | J74: =IF(H74=0,"Paid",IF(D74<TODAY(),"Overdue","Open")) -> Paid | K74: =IF(H74=0,0,MAX(0,TODAY()-D74)) -> 0 | L74: =IF(H74=0,"Paid",IF(K74<=30,"0-30 Days",IF(K74<=60,"31-60 Days",IF(K74<=90,"61-90 Days",IF(K74<=120,"91-120 Days","120+ Days"))))) -> Paid | M74: 45323 | N74: 45383
A75: INV-100074 | B75: CUST-001 | C75: 45348 | D75: 45378 | E75: 45404 | F75: 36752.96 | G75: 36752.96 | H75: =MAX(0,F75-G75) -> 0 | I75: =IF(E75="","",MAX(0,E75-D75)) -> 26 | J75: =IF(H75=0,"Paid",IF(D75<TODAY(),"Overdue","Open")) -> Paid | K75: =IF(H75=0,0,MAX(0,TODAY()-D75)) -> 0 | L75: =IF(H75=0,"Paid",IF(K75<=30,"0-30 Days",IF(K75<=60,"31-60 Days",IF(K75<=90,"61-90 Days",IF(K75<=120,"91-120 Days","120+ Days"))))) -> Paid | M75: 45323 | N75: 45383
A76: INV-100075 | B76: CUST-035 | C76: 45337 | D76: 45367 | E76: 45367 | F76: 40161.72 | G76: 40161.72 | H76: =MAX(0,F76-G76) -> 0 | I76: =IF(E76="","",MAX(0,E76-D76)) -> 0 | J76: =IF(H76=0,"Paid",IF(D76<TODAY(),"Overdue","Open")) -> Paid | K76: =IF(H76=0,0,MAX(0,TODAY()-D76)) -> 0 | L76: =IF(H76=0,"Paid",IF(K76<=30,"0-30 Days",IF(K76<=60,"31-60 Days",IF(K76<=90,"61-90 Days",IF(K76<=120,"91-120 Days","120+ Days"))))) -> Paid | M76: 45323 | N76: 45352
A77: INV-100076 | B77: CUST-029 | C77: 45343 | D77: 45373 | E77: 45374 | F77: 16910.75 | G77: 16910.75 | H77: =MAX(0,F77-G77) -> 0 | I77: =IF(E77="","",MAX(0,E77-D77)) -> 1 | J77: =IF(H77=0,"Paid",IF(D77<TODAY(),"Overdue","Open")) -> Paid | K77: =IF(H77=0,0,MAX(0,TODAY()-D77)) -> 0 | L77: =IF(H77=0,"Paid",IF(K77<=30,"0-30 Days",IF(K77<=60,"31-60 Days",IF(K77<=90,"61-90 Days",IF(K77<=120,"91-120 Days","120+ Days"))))) -> Paid | M77: 45323 | N77: 45352
A78: INV-100077 | B78: CUST-028 | C78: 45325 | D78: 45355 | E78: 45367 | F78: 98363.34 | G78: 98363.34 | H78: =MAX(0,F78-G78) -> 0 | I78: =IF(E78="","",MAX(0,E78-D78)) -> 12 | J78: =IF(H78=0,"Paid",IF(D78<TODAY(),"Overdue","Open")) -> Paid | K78: =IF(H78=0,0,MAX(0,TODAY()-D78)) -> 0 | L78: =IF(H78=0,"Paid",IF(K78<=30,"0-30 Days",IF(K78<=60,"31-60 Days",IF(K78<=90,"61-90 Days",IF(K78<=120,"91-120 Days","120+ Days"))))) -> Paid | M78: 45323 | N78: 45352
A79: INV-100078 | B79: CUST-041 | C79: 45342 | D79: 45372 | E79: 45377 | F79: 21540.73 | G79: 21540.73 | H79: =MAX(0,F79-G79) -> 0 | I79: =IF(E79="","",MAX(0,E79-D79)) -> 5 | J79: =IF(H79=0,"Paid",IF(D79<TODAY(),"Overdue","Open")) -> Paid | K79: =IF(H79=0,0,MAX(0,TODAY()-D79)) -> 0 | L79: =IF(H79=0,"Paid",IF(K79<=30,"0-30 Days",IF(K79<=60,"31-60 Days",IF(K79<=90,"61-90 Days",IF(K79<=120,"91-120 Days","120+ Days"))))) -> Paid | M79: 45323 | N79: 45352
A80: INV-100079 | B80: CUST-032 | C80: 45335 | D80: 45365 | E80: 45421 | F80: 63612.38 | G80: 63612.38 | H80: =MAX(0,F80-G80) -> 0 | I80: =IF(E80="","",MAX(0,E80-D80)) -> 56 | J80: =IF(H80=0,"Paid",IF(D80<TODAY(),"Overdue","Open")) -> Paid | K80: =IF(H80=0,0,MAX(0,TODAY()-D80)) -> 0 | L80: =IF(H80=0,"Paid",IF(K80<=30,"0-30 Days",IF(K80<=60,"31-60 Days",IF(K80<=90,"61-90 Days",IF(K80<=120,"91-120 Days","120+ Days"))))) -> Paid | M80: 45323 | N80: 45413
A81: INV-100080 | B81: CUST-044 | C81: 45342 | D81: 45372 | E81: 45385 | F81: 21197.45 | G81: 21197.45 | H81: =MAX(0,F81-G81) -> 0 | I81: =IF(E81="","",MAX(0,E81-D81)) -> 13 | J81: =IF(H81=0,"Paid",IF(D81<TODAY(),"Overdue","Open")) -> Paid | K81: =IF(H81=0,0,MAX(0,TODAY()-D81)) -> 0 | L81: =IF(H81=0,"Paid",IF(K81<=30,"0-30 Days",IF(K81<=60,"31-60 Days",IF(K81<=90,"61-90 Days",IF(K81<=120,"91-120 Days","120+ Days"))))) -> Paid | M81: 45323 | N81: 45383
A82: INV-100081 | B82: CUST-046 | C82: 45329 | D82: 45359 | E82: 45406 | F82: 45741.63 | G82: 45741.63 | H82: =MAX(0,F82-G82) -> 0 | I82: =IF(E82="","",MAX(0,E82-D82)) -> 47 | J82: =IF(H82=0,"Paid",IF(D82<TODAY(),"Overdue","Open")) -> Paid | K82: =IF(H82=0,0,MAX(0,TODAY()-D82)) -> 0 | L82: =IF(H82=0,"Paid",IF(K82<=30,"0-30 Days",IF(K82<=60,"31-60 Days",IF(K82<=90,"61-90 Days",IF(K82<=120,"91-120 Days","120+ Days"))))) -> Paid | M82: 45323 | N82: 45383
... A84: INV-100083 | B84: CUST-048 | C84: 45329 | D84: 45359 | E84: 45364 | F84: 70475.88 | G84: 70475.88 | H84: =MAX(0,F84-G84) -> 0 | I84: =IF(E84="","",MAX(0,E84-D84)) -> 5 | J84: =IF(H84=0,"Paid",IF(D84<TODAY(),"Overdue","Open")) -> Paid | K84: =IF(H84=0,0,MAX(0,TODAY()-D84)) -> 0 | L84: =IF(H84=0,"Paid",IF(K84<=30,"0-30 Days",IF(K84<=60,"31-60 Days",IF(K84<=90,"61-90 Days",IF(K84<=120,"91-120 Days","120+ Days"))))) -> Paid | M84: 45323 | N84: 45352
A85: INV-100084 | B85: CUST-032 | C85: 45340 | D85: 45370 | F85: 46250.46 | G85: 0 | H85: =MAX(0,F85-G85) -> 46250.46 | I85: =IF(E85="","",MAX(0,E85-D85)) | J85: =IF(H85=0,"Paid",IF(D85<TODAY(),"Overdue","Open")) -> Overdue | K85: =IF(H85=0,0,MAX(0,TODAY()-D85)) -> 886 | L85: =IF(H85=0,"Paid",IF(K85<=30,"0-30 Days",IF(K85<=60,"31-60 Days",IF(K85<=90,"61-90 Days",IF(K85<=120,"91-120 Days","120+ Days"))))) -> 120+ Days | M85: 45323
A86: INV-100085 | B86: CUST-030 | C86: 45326 | D86: 45356 | E86: 45400 | F86: 39662.43 | G86: 39662.43 | H86: =MAX(0,F86-G86) -> 0 | I86: =IF(E86="","",MAX(0,E86-D86)) -> 44 | J86: =IF(H86=0,"Paid",IF(D86<TODAY(),"Overdue","Open")) -> Paid | K86: =IF(H86=0,0,MAX(0,TODAY()-D86)) -> 0 | L86: =IF(H86=0,"Paid",IF(K86<=30,"0-30 Days",IF(K86<=60,"31-60 Days",IF(K86<=90,"61-90 Days",IF(K86<=120,"91-120 Days","120+ Days"))))) -> Paid | M86: 45323 | N86: 45383
A87: INV-100086 | B87: CUST-015 | C87: 45326 | D87: 45356 | E87: 45362 | F87: 23977.87 | G87: 23977.87 | H87: =MAX(0,F87-G87) -> 0 | I87: =IF(E87="","",MAX(0,E87-D87)) -> 6 | J87: =IF(H87=0,"Paid",IF(D87<TODAY(),"Overdue","Open")) -> Paid | K87: =IF(H87=0,0,MAX(0,TODAY()-D87)) -> 0 | L87: =IF(H87=0,"Paid",IF(K87<=30,"0-30 Days",IF(K87<=60,"31-60 Days",IF(K87<=90,"61-90 Days",IF(K87<=120,"91-120 Days","120+ Days"))))) -> Paid | M87: 45323 | N87: 45352
A88: INV-100087 | B88: CUST-036 | C88: 45349 | D88: 45379 | E88: 45379 | F88: 24140.52 | G88: 24140.52 | H88: =MAX(0,F88-G88) -> 0 | I88: =IF(E88="","",MAX(0,E88-D88)) -> 0 | J88: =IF(H88=0,"Paid",IF(D88<TODAY(),"Overdue","Open")) -> Paid | K88: =IF(H88=0,0,MAX(0,TODAY()-D88)) -> 0 | L88: =IF(H88=0,"Paid",IF(K88<=30,"0-30 Days",IF(K88<=60,"31-60 Days",IF(K88<=90,"61-90 Days",IF(K88<=120,"91-120 Days","120+ Days"))))) -> Paid | M88: 45323 | N88: 45352
A89: INV-100088 | B89: CUST-009 | C89: 45334 | D89: 45364 | E89: 45366 | F89: 20649.34 | G89: 20649.34 | H89: =MAX(0,F89-G89) -> 0 | I89: =IF(E89="","",MAX(0,E89-D89)) -> 2 | J89: =IF(H89=0,"Paid",IF(D89<TODAY(),"Overdue","Open")) -> Paid | K89: =IF(H89=0,0,MAX(0,TODAY()-D89)) -> 0 | L89: =IF(H89=0,"Paid",IF(K89<=30,"0-30 Days",IF(K89<=60,"31-60 Days",IF(K89<=90,"61-90 Days",IF(K89<=120,"91-120 Days","120+ Days"))))) -> Paid | M89: 45323 | N89: 45352
A90: INV-100089 | B90: CUST-056 | C90: 45335 | D90: 45365 | E90: 45398 | F90: 70143.35 | G90: 70143.35 | H90: =MAX(0,F90-G90) -> 0 | I90: =IF(E90="","",MAX(0,E90-D90)) -> 33 | J90: =IF(H90=0,"Paid",IF(D90<TODAY(),"Overdue","Open")) -> Paid | K90: =IF(H90=0,0,MAX(0,TODAY()-D90)) -> 0 | L90: =IF(H90=0,"Paid",IF(K90<=30,"0-30 Days",IF(K90<=60,"31-60 Days",IF(K90<=90,"61-90 Days",IF(K90<=120,"91-120 Days","120+ Days"))))) -> Paid | M90: 45323 | N90: 45383
A91: INV-100090 | B91: CUST-051 | C91: 45335 | D91: 45365 | E91: 45374 | F91: 30519.07 | G91: 30519.07 | H91: =MAX(0,F91-G91) -> 0 | I91: =IF(E91="","",MAX(0,E91-D91)) -> 9 | J91: =IF(H91=0,"Paid",IF(D91<TODAY(),"Overdue","Open")) -> Paid | K91: =IF(H91=0,0,MAX(0,TODAY()-D91)) -> 0 | L91: =IF(H91=0,"Paid",IF(K91<=30,"0-30 Days",IF(K91<=60,"31-60 Days",IF(K91<=90,"61-90 Days",IF(K91<=120,"91-120 Days","120+ Days"))))) -> Paid | M91: 45323 | N91: 45352
A92: INV-100091 | B92: CUST-008 | C92: 45339 | D92: 45369 | E92: 45379 | F92: 31678.95 | G92: 31678.95 | H92: =MAX(0,F92-G92) -> 0 | I92: =IF(E92="","",MAX(0,E92-D92)) -> 10 | J92: =IF(H92=0,"Paid",IF(D92<TODAY(),"Overdue","Open")) -> Paid | K92: =IF(H92=0,0,MAX(0,TODAY()-D92)) -> 0 | L92: =IF(H92=0,"Paid",IF(K92<=30,"0-30 Days",IF(K92<=60,"31-60 Days",IF(K92<=90,"61-90 Days",IF(K92<=120,"91-120 Days","120+ Days"))))) -> Paid | M92: 45323 | N92: 45352
A93: INV-100092 | B93: CUST-048 | C93: 45331 | D93: 45361 | E93: 45371 | F93: 38310.78 | G93: 38310.78 | H93: =MAX(0,F93-G93) -> 0 | I93: =IF(E93="","",MAX(0,E93-D93)) -> 10 | J93: =IF(H93=0,"Paid",IF(D93<TODAY(),"Overdue","Open")) -> Paid | K93: =IF(H93=0,0,MAX(0,TODAY()-D93)) -> 0 | L93: =IF(H93=0,"Paid",IF(K93<=30,"0-30 Days",IF(K93<=60,"31-60 Days",IF(K93<=90,"61-90 Days",IF(K93<=120,"91-120 Days","120+ Days"))))) -> Paid | M93: 45323 | N93: 45352
A94: INV-100093 | B94: CUST-008 | C94: 45344 | D94: 45374 | F94: 40148.33 | G94: 0 | H94: =MAX(0,F94-G94) -> 40148.33 | I94: =IF(E94="","",MAX(0,E94-D94)) | J94: =IF(H94=0,"Paid",IF(D94<TODAY(),"Overdue","Open")) -> Overdue | K94: =IF(H94=0,0,MAX(0,TODAY()-D94)) -> 882 | L94: =IF(H94=0,"Paid",IF(K94<=30,"0-30 Days",IF(K94<=60,"31-60 Days",IF(K94<=90,"61-90 Days",IF(K94<=120,"91-120 Days","120+ Days"))))) -> 120+ Days | M94: 45323
A95: INV-100094 | B95: CUST-044 | C95: 45342 | D95: 45372 | E95: 45372 | F95: 37003.55 | G95: 37003.55 | H95: =MAX(0,F95-G95) -> 0 | I95: =IF(E95="","",MAX(0,E95-D95)) -> 0 | J95: =IF(H95=0,"Paid",IF(D95<TODAY(),"Overdue","Open")) -> Paid | K95: =IF(H95=0,0,MAX(0,TODAY()-D95)) -> 0 | L95: =IF(H95=0,"Paid",IF(K95<=30,"0-30 Days",IF(K95<=60,"31-60 Days",IF(K95<=90,"61-90 Days",IF(K95<=120,"91-120 Days","120+ Days"))))) -> Paid | M95: 45323 | N95: 45352
A96: INV-100095 | B96: CUST-006 | C96: 45329 | D96: 45359 | F96: 23900.5 | G96: 0 | H96: =MAX(0,F96-G96) -> 23900.5 | I96: =IF(E96="","",MAX(0,E96-D96)) | J96: =IF(H96=0,"Paid",IF(D96<TODAY(),"Overdue","Open")) -> Overdue | K96: =IF(H96=0,0,MAX(0,TODAY()-D96)) -> 897 | L96: =IF(H96=0,"Paid",IF(K96<=30,"0-30 Days",IF(K96<=60,"31-60 Days",IF(K96<=90,"61-90 Days",IF(K96<=120,"91-120 Days","120+ Days"))))) -> 120+ Days | M96: 45323
A97: INV-100096 | B97: CUST-030 | C97: 45331 | D97: 45361 | E97: 45405 | F97: 53469.53 | G97: 53469.53 | H97: =MAX(0,F97-G97) -> 0 | I97: =IF(E97="","",MAX(0,E97-D97)) -> 44 | J97: =IF(H97=0,"Paid",IF(D97<TODAY(),"Overdue","Open")) -> Paid | K97: =IF(H97=0,0,MAX(0,TODAY()-D97)) -> 0 | L97: =IF(H97=0,"Paid",IF(K97<=30,"0-30 Days",IF(K97<=60,"31-60 Days",IF(K97<=90,"61-90 Days",IF(K97<=120,"91-120 Days","120+ Days"))))) -> Paid | M97: 45323 | N97: 45383
A98: INV-100097 | B98: CUST-040 | C98: 45345 | D98: 45375 | E98: 45398 | F98: 32616.16 | G98: 32616.16 | H98: =MAX(0,F98-G98) -> 0 | I98: =IF(E98="","",MAX(0,E98-D98)) -> 23 | J98: =IF(H98=0,"Paid",IF(D98<TODAY(),"Overdue","Open")) -> Paid | K98: =IF(H98=0,0,MAX(0,TODAY()-D98)) -> 0 | L98: =IF(H98=0,"Paid",IF(K98<=30,"0-30 Days",IF(K98<=60,"31-60 Days",IF(K98<=90,"61-90 Days",IF(K98<=120,"91-120 Days","120+ Days"))))) -> Paid | M98: 45323 | N98: 45383
A99: INV-100098 | B99: CUST-044 | C99: 45324 | D99: 45354 | E99: 45355 | F99: 63866.54 | G99: 63866.54 | H99: =MAX(0,F99-G99) -> 0 | I99: =IF(E99="","",MAX(0,E99-D99)) -> 1 | J99: =IF(H99=0,"Paid",IF(D99<TODAY(),"Overdue","Open")) -> Paid | K99: =IF(H99=0,0,MAX(0,TODAY()-D99)) -> 0 | L99: =IF(H99=0,"Paid",IF(K99<=30,"0-30 Days",IF(K99<=60,"31-60 Days",IF(K99<=90,"61-90 Days",IF(K99<=120,"91-120 Days","120+ Days"))))) -> Paid | M99: 45323 | N99: 45352
A100: INV-100099 | B100: CUST-026 | C100: 45334 | D100: 45364 | E100: 45384 | F100: 16776.2 | G100: 16776.2 | H100: =MAX(0,F100-G100) -> 0 | I100: =IF(E100="","",MAX(0,E100-D100)) -> 20 | J100: =IF(H100=0,"Paid",IF(D100<TODAY(),"Overdue","Open")) -> Paid | K100: =IF(H100=0,0,MAX(0,TODAY()-D100)) -> 0 | L100: =IF(H100=0,"Paid",IF(K100<=30,"0-30 Days",IF(K100<=60,"31-60 Days",IF(K100<=90,"61-90 Days",IF(K100<=120,"91-120 Days","120+ Days"))))) -> Paid | M100: 45323 | N100: 45383
A101: INV-100100 | B101: CUST-056 | C101: 45345 | D101: 45375 | E101: 45375 | F101: 25701.02 | G101: 25701.02 | H101: =MAX(0,F101-G101) -> 0 | I101: =IF(E101="","",MAX(0,E101-D101)) -> 0 | J101: =IF(H101=0,"Paid",IF(D101<TODAY(),"Overdue","Open")) -> Paid | K101: =IF(H101=0,0,MAX(0,TODAY()-D101)) -> 0 | L101: =IF(H101=0,"Paid",IF(K101<=30,"0-30 Days",IF(K101<=60,"31-60 Days",IF(K101<=90,"61-90 Days",IF(K101<=120,"91-120 Days","120+ Days"))))) -> Paid | M101: 45323 | N101: 45352
...

Sheet Clean_Expenses
A1: Expense_ID | B1: Expense_Date | C1: Department | D1: Category | E1: Actual_Expense | F1: Vendor_ID
A2: EXP-500001 | B2: 45292 | C2: IT | D2: Salaries | E2: 95356.73 | F2: VEND-121
A3: EXP-500002 | B3: 45301 | C3: IT | D3: Rent | E3: 23332.26 | F3: VEND-121
A4: EXP-500003 | B4: 45292 | C4: IT | D4: Utilities | E4: 8620.85 | F4: VEND-134
A5: EXP-500004 | B5: 45297 | C5: IT | D5: Software | E5: 13851.81 | F5: VEND-172
A6: EXP-500005 | B6: 45306 | C6: IT | D6: Marketing | E6: 17657.69 | F6: VEND-146
A7: EXP-500006 | B7: 45302 | C7: IT | D7: Travel | E7: 9372.01 | F7: VEND-155
A8: EXP-500007 | B8: 45308 | C8: IT | D8: Operations | E8: 17872.04 | F8: VEND-104
A9: EXP-500008 | B9: 45309 | C9: IT | D9: Taxes | E9: 7163.76 | F9: VEND-146
A10: EXP-500009 | B10: 45304 | C10: IT | D10: Other | E10: 6963.31 | F10: VEND-121
A11: EXP-500010 | B11: 45317 | C11: HR | D11: Salaries | E11: 38877.17 | F11: VEND-156
A12: EXP-500011 | B12: 45293 | C12: HR | D12: Rent | E12: 9952.18 | F12: VEND-130
A13: EXP-500012 | B13: 45311 | C13: HR | D13: Utilities | E13: 3728.38 | F13: VEND-165
... A1513: EXP-501512 | B1513: 45996 | C1513: Sales | D1513: Other | E1513: 4003.91 | F1513: VEND-111

Sheet Budgets
A1: Month | B1: Department | C1: Category | D1: Budget
A2: 45292 | B2: Administration | C2: Operations | D2: 7172.8
A3: 45292 | B3: Administration | C3: Other | D3: 2287.23
A4: 45292 | B4: IT | C4: Salaries | D4: 103935.79
A5: 45292 | B5: IT | C5: Utilities | D5: 8702.9
A6: 45292 | B6: Operations | C6: Utilities | D6: 8807.78
A7: 45292 | B7: Administration | C7: Taxes | D7: 2500.19
A8: 45292 | B8: HR | C8: Rent | D8: 9395.31
A9: 45292 | B9: Marketing | C9: Rent | D9: 15466.21
A10: 45292 | B10: Marketing | C10: Travel | D10: 8146.36
A11: 45292 | B11: Operations | C11: Operations | D11: 18171.09
A12: 45292 | B12: Sales | C12: Rent | D12: 13269.64
A13: 45292 | B13: Administration | C13: Utilities | D13: 4152.17
... A1513: 45992 | B1513: Operations | C1513: Taxes | D1513: 5838.96

Sheet Customer_Master
A1: Customer_ID | B1: Customer_Name | C1: Segment | D1: Base_Risk
A2: CUST-001 | B2: Customer 001 | C2: SMB | D2: Medium
A3: CUST-002 | B3: Customer 002 | C3: SMB | D3: Low
A4: CUST-003 | B4: Customer 003 | C4: SMB | D4: Medium
A5: CUST-004 | B5: Customer 004 | C5: Mid-Market | D5: Medium
A6: CUST-005 | B6: Customer 005 | C6: SMB | D6: Low
A7: CUST-006 | B7: Customer 006 | C7: SMB | D7: High
A8: CUST-007 | B8: Customer 007 | C8: SMB | D8: Medium
A9: CUST-008 | B9: Customer 008 | C9: SMB | D9: Medium
A10: CUST-009 | B10: Customer 009 | C10: Enterprise | D10: Low
A11: CUST-010 | B11: Customer 010 | C11: SMB | D11: Low
A12: CUST-011 | B12: Customer 011 | C12: Enterprise | D12: Low
... A61: CUST-060 | B61: Customer 060 | C61: SMB | D61: Low

Sheet Revenue_Collections
A1: Invoice_Month | B1: Revenue | C1: Collected | D1: Outstanding | E1: Collection_Efficiency_% | F1: MoM_Revenue_Growth_%
A2: 45292 | B2: =SUMIFS(Clean_AR_Data!$F:$F,Clean_AR_Data!$C:$C,">="&A2,Clean_AR_Data!$C:$C,"<"&EDATE(A2,1)) -> 2685331 | C2: =SUMIFS(Clean_AR_Data!$G:$G,Clean_AR_Data!$E:$E,">="&A2,Clean_AR_Data!$E:$E,"<"&EDATE(A2,1)) -> 0 | D2: =SUMIFS(Clean_AR_Data!$H:$H,Clean_AR_Data!$C:$C,">="&A2,Clean_AR_Data!$C:$C,"<"&EDATE(A2,1)) -> 798551.31 | E2: =IFERROR(C2/B2,0) -> 0
A3: 45323 | B3: =SUMIFS(Clean_AR_Data!$F:$F,Clean_AR_Data!$C:$C,">="&A3,Clean_AR_Data!$C:$C,"<"&EDATE(A3,1)) -> 3604285.4 | C3: =SUMIFS(Clean_AR_Data!$G:$G,Clean_AR_Data!$E:$E,">="&A3,Clean_AR_Data!$E:$E,"<"&EDATE(A3,1)) -> 1498657.4 | D3: =SUMIFS(Clean_AR_Data!$H:$H,Clean_AR_Data!$C:$C,">="&A3,Clean_AR_Data!$C:$C,"<"&EDATE(A3,1)) -> 819364.98 | E3: =IFERROR(C3/B3,0) -> 0.41579877 | F3: 34.221271
A4: 45352 | B4: =SUMIFS(Clean_AR_Data!$F:$F,Clean_AR_Data!$C:$C,">="&A4,Clean_AR_Data!$C:$C,"<"&EDATE(A4,1)) -> 2936541.5 | C4: =SUMIFS(Clean_AR_Data!$G:$G,Clean_AR_Data!$E:$E,">="&A4,Clean_AR_Data!$E:$E,"<"&EDATE(A4,1)) -> 2156419.9 | D4: =SUMIFS(Clean_AR_Data!$H:$H,Clean_AR_Data!$C:$C,">="&A4,Clean_AR_Data!$C:$C,"<"&EDATE(A4,1)) -> 1067326.9 | E4: =IFERROR(C4/B4,0) -> 0.73434 | F4: -18.526388
A5: 45383 | B5: =SUMIFS(Clean_AR_Data!$F:$F,Clean_AR_Data!$C:$C,">="&A5,Clean_AR_Data!$C:$C,"<"&EDATE(A5,1)) -> 2893620.9 | C5: =SUMIFS(Clean_AR_Data!$G:$G,Clean_AR_Data!$E:$E,">="&A5,Clean_AR_Data!$E:$E,"<"&EDATE(A5,1)) -> 1818535 | D5: =SUMIFS(Clean_AR_Data!$H:$H,Clean_AR_Data!$C:$C,">="&A5,Clean_AR_Data!$C:$C,"<"&EDATE(A5,1)) -> 832177.61 | E5: =IFERROR(C5/B5,0) -> 0.62846347 | F5: -1.461602
A6: 45413 | B6: =SUMIFS(Clean_AR_Data!$F:$F,Clean_AR_Data!$C:$C,">="&A6,Clean_AR_Data!$C:$C,"<"&EDATE(A6,1)) -> 3452600.6 | C6: =SUMIFS(Clean_AR_Data!$G:$G,Clean_AR_Data!$E:$E,">="&A6,Clean_AR_Data!$E:$E,"<"&EDATE(A6,1)) -> 2217910.1 | D6: =SUMIFS(Clean_AR_Data!$H:$H,Clean_AR_Data!$C:$C,">="&A6,Clean_AR_Data!$C:$C,"<"&EDATE(A6,1)) -> 845354.09 | E6: =IFERROR(C6/B6,0) -> 0.64238826 | F6: 19.317654
A7: 45444 | B7: =SUMIFS(Clean_AR_Data!$F:$F,Clean_AR_Data!$C:$C,">="&A7,Clean_AR_Data!$C:$C,"<"&EDATE(A7,1)) -> 2919269.1 | C7: =SUMIFS(Clean_AR_Data!$G:$G,Clean_AR_Data!$E:$E,">="&A7,Clean_AR_Data!$E:$E,"<"&EDATE(A7,1)) -> 1754014.9 | D7: =SUMIFS(Clean_AR_Data!$H:$H,Clean_AR_Data!$C:$C,">="&A7,Clean_AR_Data!$C:$C,"<"&EDATE(A7,1)) -> 807622.7 | E7: =IFERROR(C7/B7,0) -> 0.60084043 | F7: -15.447242
A8: 45474 | B8: =SUMIFS(Clean_AR_Data!$F:$F,Clean_AR_Data!$C:$C,">="&A8,Clean_AR_Data!$C:$C,"<"&EDATE(A8,1)) -> 2254535.9 | C8: =SUMIFS(Clean_AR_Data!$G:$G,Clean_AR_Data!$E:$E,">="&A8,Clean_AR_Data!$E:$E,"<"&EDATE(A8,1)) -> 3112048.1 | D8: =SUMIFS(Clean_AR_Data!$H:$H,Clean_AR_Data!$C:$C,">="&A8,Clean_AR_Data!$C:$C,"<"&EDATE(A8,1)) -> 296119.25 | E8: =IFERROR(C8/B8,0) -> 1.3803498 | F8: -22.770535
A9: 45505 | B9: =SUMIFS(Clean_AR_Data!$F:$F,Clean_AR_Data!$C:$C,">="&A9,Clean_AR_Data!$C:$C,"<"&EDATE(A9,1)) -> 3024137.9 | C9: =SUMIFS(Clean_AR_Data!$G:$G,Clean_AR_Data!$E:$E,">="&A9,Clean_AR_Data!$E:$E,"<"&EDATE(A9,1)) -> 1617432.3 | D9: =SUMIFS(Clean_AR_Data!$H:$H,Clean_AR_Data!$C:$C,">="&A9,Clean_AR_Data!$C:$C,"<"&EDATE(A9,1)) -> 885006.64 | E9: =IFERROR(C9/B9,0) -> 0.53484079 | F9: 34.13572
A10: 45536 | B10: =SUMIFS(Clean_AR_Data!$F:$F,Clean_AR_Data!$C:$C,">="&A10,Clean_AR_Data!$C:$C,"<"&EDATE(A10,1)) -> 3423493.2 | C10: =SUMIFS(Clean_AR_Data!$G:$G,Clean_AR_Data!$E:$E,">="&A10,Clean_AR_Data!$E:$E,"<"&EDATE(A10,1)) -> 2296144.8 | D10: =SUMIFS(Clean_AR_Data!$H:$H,Clean_AR_Data!$C:$C,">="&A10,Clean_AR_Data!$C:$C,"<"&EDATE(A10,1)) -> 1056246.6 | E10: =IFERROR(C10/B10,0) -> 0.6707023 | F10: 13.205591
A11: 45566 | B11: =SUMIFS(Clean_AR_Data!$F:$F,Clean_AR_Data!$C:$C,">="&A11,Clean_AR_Data!$C:$C,"<"&EDATE(A11,1)) -> 3273949.7 | C11: =SUMIFS(Clean_AR_Data!$G:$G,Clean_AR_Data!$E:$E,">="&A11,Clean_AR_Data!$E:$E,"<"&EDATE(A11,1)) -> 1893766.4 | D11: =SUMIFS(Clean_AR_Data!$H:$H,Clean_AR_Data!$C:$C,">="&A11,Clean_AR_Data!$C:$C,"<"&EDATE(A11,1)) -> 899438.7 | E11: =IFERROR(C11/B11,0) -> 0.57843477 | F11: -4.3681561
A12: 45597 | B12: =SUMIFS(Clean_AR_Data!$F:$F,Clean_AR_Data!$C:$C,">="&A12,Clean_AR_Data!$C:$C,"<"&EDATE(A12,1)) -> 2784229.9 | C12: =SUMIFS(Clean_AR_Data!$G:$G,Clean_AR_Data!$E:$E,">="&A12,Clean_AR_Data!$E:$E,"<"&EDATE(A12,1)) -> 2599084.3 | D12: =SUMIFS(Clean_AR_Data!$H:$H,Clean_AR_Data!$C:$C,">="&A12,Clean_AR_Data!$C:$C,"<"&EDATE(A12,1)) -> 525078.5 | E12: =IFERROR(C12/B12,0) -> 0.93350204 | F12: -14.958072
A13: 45627 | B13: =SUMIFS(Clean_AR_Data!$F:$F,Clean_AR_Data!$C:$C,">="&A13,Clean_AR_Data!$C:$C,"<"&EDATE(A13,1)) -> 2513728.5 | C13: =SUMIFS(Clean_AR_Data!$G:$G,Clean_AR_Data!$E:$E,">="&A13,Clean_AR_Data!$E:$E,"<"&EDATE(A13,1)) -> 2048794.4 | D13: =SUMIFS(Clean_AR_Data!$H:$H,Clean_AR_Data!$C:$C,">="&A13,Clean_AR_Data!$C:$C,"<"&EDATE(A13,1)) -> 547106.34 | E13: =IFERROR(C13/B13,0) -> 0.81504203 | F13: -9.7154838
A14: 45658 | B14: =SUMIFS(Clean_AR_Data!$F:$F,Clean_AR_Data!$C:$C,">="&A14,Clean_AR_Data!$C:$C,"<"&EDATE(A14,1)) -> 2724300.6 | C14: =SUMIFS(Clean_AR_Data!$G:$G,Clean_AR_Data!$E:$E,">="&A14,Clean_AR_Data!$E:$E,"<"&EDATE(A14,1)) -> 2105588.5 | D14: =SUMIFS(Clean_AR_Data!$H:$H,Clean_AR_Data!$C:$C,">="&A14,Clean_AR_Data!$C:$C,"<"&EDATE(A14,1)) -> 871710.85 | E14: =IFERROR(C14/B14,0) -> 0.77289139 | F14: 8.3768819
... A25: 45992 | B25: =SUMIFS(Clean_AR_Data!$F:$F,Clean_AR_Data!$C:$C,">="&A25,Clean_AR_Data!$C:$C,"<"&EDATE(A25,1)) -> 3242803.2 | C25: =SUMIFS(Clean_AR_Data!$G:$G,Clean_AR_Data!$E:$E,">="&A25,Clean_AR_Data!$E:$E,"<"&EDATE(A25,1)) -> 2263449.7 | D25: =SUMIFS(Clean_AR_Data!$H:$H,Clean_AR_Data!$C:$C,">="&A25,Clean_AR_Data!$C:$C,"<"&EDATE(A25,1)) -> 822794.63 | E25: =IFERROR(C25/B25,0) -> 0.69799169 | F25: -16.979223

Sheet AR_Ageing
A1: Age_Bucket | B1: Outstanding | C1: Invoice_Count | D1: %_of_Total_AR
A2: 0-30 | B2: =SUMIFS(Clean_AR_Data!$H:$H,Clean_AR_Data!$L:$L,A2) -> 0 | C2: =COUNTIFS(Clean_AR_Data!$L:$L,A2) -> 0 | D2: =IFERROR(B2/SUM($B$2:$B$6),0) -> 0
A3: 31-60 | B3: =SUMIFS(Clean_AR_Data!$H:$H,Clean_AR_Data!$L:$L,A3) -> 0 | C3: =COUNTIFS(Clean_AR_Data!$L:$L,A3) -> 0 | D3: =IFERROR(B3/SUM($B$2:$B$6),0) -> 0
A4: 61-90 | B4: =SUMIFS(Clean_AR_Data!$H:$H,Clean_AR_Data!$L:$L,A4) -> 0 | C4: =COUNTIFS(Clean_AR_Data!$L:$L,A4) -> 0 | D4: =IFERROR(B4/SUM($B$2:$B$6),0) -> 0
A5: 91-120 | B5: =SUMIFS(Clean_AR_Data!$H:$H,Clean_AR_Data!$L:$L,A5) -> 0 | C5: =COUNTIFS(Clean_AR_Data!$L:$L,A5) -> 0 | D5: =IFERROR(B5/SUM($B$2:$B$6),0) -> 0
A6: 120+ | B6: =SUMIFS(Clean_AR_Data!$H:$H,Clean_AR_Data!$L:$L,A6) -> 0 | C6: =COUNTIFS(Clean_AR_Data!$L:$L,A6) -> 0 | D6: =IFERROR(B6/SUM($B$2:$B$6),0) -> 0

Sheet Customer_Risk
A1: Customer_ID | B1: Total_Invoiced | C1: Total_Collected | D1: Outstanding | E1: Avg_Payment_Delay | F1: Overdue_Invoices | G1: Invoice_Count | H1: Collection_Efficiency_% | I1: Risk_Score | J1: Risk_Class | K1: Customer_Name | L1: Segment
A2: CUST-006 | B2: 1254372.6 | C2: 307435.02 | D2: 946937.53 | E2: 336.93103 | F2: 20 | G2: 29 | H2: 24.509068 | I2: 95.098186 | J2: High | K2: Customer 006 | L2: SMB
A3: CUST-012 | B3: 1071011.4 | C3: 460539.27 | D3: 610472.16 | E3: 200.96154 | F3: 13 | G3: 26 | H3: 43.000407 | I3: 91.399919 | J3: High | K3: Customer 012 | L3: SMB
A4: CUST-030 | B4: 1314474.1 | C4: 742712.65 | D4: 571761.49 | E4: 197.88889 | F4: 14 | G4: 27 | H4: 56.502644 | I4: 88.699471 | J4: High | K4: Customer 030 | L4: SMB
A5: CUST-023 | B5: 846642.46 | C5: 330349.46 | D5: 516293 | E5: 199.41667 | F5: 14 | G5: 24 | H5: 39.018768 | I5: 87.97418 | J5: High | K5: Customer 023 | L5: Mid-Market
A6: CUST-032 | B6: 1507836.7 | C6: 833119.16 | D6: 674717.57 | E6: 178.75 | F6: 18 | G6: 36 | H6: 55.252611 | I6: 87.110158 | J6: High | K6: Customer 032 | L6: SMB
A7: CUST-008 | B7: 1321370.5 | C7: 670444.06 | D7: 650926.45 | E7: 173.85714 | F7: 14 | G7: 28 | H7: 50.738537 | I7: 87.105278 | J7: High | K7: Customer 008 | L7: SMB
A8: CUST-056 | B8: 1142424.4 | C8: 586020.61 | D8: 556403.81 | E8: 165.15385 | F8: 12 | G8: 26 | H8: 51.296226 | I8: 84.325127 | J8: High | K8: Customer 056 | L8: Mid-Market
A9: CUST-021 | B9: 1750160.7 | C9: 1163035.2 | D9: 587125.5 | E9: 143.37838 | F9: 15 | G9: 37 | H9: 66.453052 | I9: 78.308128 | J9: High | K9: Customer 021 | L9: SMB
A10: CUST-054 | B10: 749996.54 | C10: 383467.27 | D10: 366529.27 | E10: 199.68182 | F10: 11 | G10: 22 | H10: 51.129205 | I10: 73.723431 | J10: High | K10: Customer 054 | L10: SMB
A11: CUST-007 | B11: 1196416.9 | C11: 665216.03 | D11: 531200.82 | E11: 122.88889 | F11: 11 | G11: 27 | H11: 55.600691 | I11: 73.632893 | J11: High | K11: Customer 007 | L11: SMB
A12: CUST-055 | B12: 646060.39 | C12: 298330.29 | D12: 347730.1 | E12: 187.64706 | F12: 10 | G12: 17 | H12: 46.176843 | I12: 73.040316 | J12: High | K12: Customer 055 | L12: Enterprise
A13: CUST-046 | B13: 1582213 | C13: 1020573.1 | D13: 561639.95 | E13: 114.14286 | F13: 9 | G13: 35 | H13: 64.502887 | I13: 72.634088 | J13: High | K13: Customer 046 | L13: SMB
... A61: CUST-041 | B61: 837528.86 | C61: 837528.86 | D61: 0 | E61: 10.652174 | F61: 0 | G61: 23 | H61: 100 | I61: 1.9761305 | J61: Low | K61: Customer 041 | L61: Mid-Market

Sheet Budget_vs_Actual
A1: Month | B1: Department | C1: Category | D1: Budget | E1: Actual_Expense | F1: Variance | G1: Variance_% | H1: Budget_Status
A2: 45292 | B2: Administration | C2: Operations | D2: 7172.8 | E2: 6539.45 | F2: =E2-D2 -> -633.35 | G2: =IFERROR(F2/D2,0) -> -0.088298851 | H2: =IF(G2<=0,"Under Budget",IF(G2<=5%,"Within Budget",IF(G2<=15%,"Slightly Over","Significantly Over"))) -> Under Budget
A3: 45292 | B3: Administration | C3: Other | D3: 2287.23 | E3: 2480.19 | F3: =E3-D3 -> 192.96 | G3: =IFERROR(F3/D3,0) -> 0.084364056 | H3: =IF(G3<=0,"Under Budget",IF(G3<=5%,"Within Budget",IF(G3<=15%,"Slightly Over","Significantly Over"))) -> Slightly Over
A4: 45292 | B4: IT | C4: Salaries | D4: 103935.79 | E4: 95356.73 | F4: =E4-D4 -> -8579.06 | G4: =IFERROR(F4/D4,0) -> -0.082541923 | H4: =IF(G4<=0,"Under Budget",IF(G4<=5%,"Within Budget",IF(G4<=15%,"Slightly Over","Significantly Over"))) -> Under Budget
A5: 45292 | B5: IT | C5: Utilities | D5: 8702.9 | E5: 8620.85 | F5: =E5-D5 -> -82.05 | G5: =IFERROR(F5/D5,0) -> -0.0094278919 | H5: =IF(G5<=0,"Under Budget",IF(G5<=5%,"Within Budget",IF(G5<=15%,"Slightly Over","Significantly Over"))) -> Under Budget
A6: 45292 | B6: Operations | C6: Utilities | D6: 8807.78 | E6: 8858.25 | F6: =E6-D6 -> 50.47 | G6: =IFERROR(F6/D6,0) -> 0.0057301613 | H6: =IF(G6<=0,"Under Budget",IF(G6<=5%,"Within Budget",IF(G6<=15%,"Slightly Over","Significantly Over"))) -> Within Budget
A7: 45292 | B7: Administration | C7: Taxes | D7: 2500.19 | E7: 2475.08 | F7: =E7-D7 -> -25.11 | G7: =IFERROR(F7/D7,0) -> -0.010043237 | H7: =IF(G7<=0,"Under Budget",IF(G7<=5%,"Within Budget",IF(G7<=15%,"Slightly Over","Significantly Over"))) -> Under Budget
A8: 45292 | B8: HR | C8: Rent | D8: 9395.31 | E8: 9952.18 | F8: =E8-D8 -> 556.87 | G8: =IFERROR(F8/D8,0) -> 0.059271062 | H8: =IF(G8<=0,"Under Budget",IF(G8<=5%,"Within Budget",IF(G8<=15%,"Slightly Over","Significantly Over"))) -> Slightly Over
A9: 45292 | B9: Marketing | C9: Rent | D9: 15466.21 | E9: 15455.53 | F9: =E9-D9 -> -10.68 | G9: =IFERROR(F9/D9,0) -> -0.00069053763 | H9: =IF(G9<=0,"Under Budget",IF(G9<=5%,"Within Budget",IF(G9<=15%,"Slightly Over","Significantly Over"))) -> Under Budget
A10: 45292 | B10: Marketing | C10: Travel | D10: 8146.36 | E10: 7494.78 | F10: =E10-D10 -> -651.58 | G10: =IFERROR(F10/D10,0) -> -0.079984189 | H10: =IF(G10<=0,"Under Budget",IF(G10<=5%,"Within Budget",IF(G10<=15%,"Slightly Over","Significantly Over"))) -> Under Budget
A11: 45292 | B11: Operations | C11: Operations | D11: 18171.09 | E11: 16884.33 | F11: =E11-D11 -> -1286.76 | G11: =IFERROR(F11/D11,0) -> -0.070813584 | H11: =IF(G11<=0,"Under Budget",IF(G11<=5%,"Within Budget",IF(G11<=15%,"Slightly Over","Significantly Over"))) -> Under Budget
A12: 45292 | B12: Sales | C12: Rent | D12: 13269.64 | E12: 14178.92 | F12: =E12-D12 -> 909.28 | G12: =IFERROR(F12/D12,0) -> 0.068523336 | H12: =IF(G12<=0,"Under Budget",IF(G12<=5%,"Within Budget",IF(G12<=15%,"Slightly Over","Significantly Over"))) -> Slightly Over
A13: 45292 | B13: Administration | C13: Utilities | D13: 4152.17 | E13: 3961.42 | F13: =E13-D13 -> -190.75 | G13: =IFERROR(F13/D13,0) -> -0.045939834 | H13: =IF(G13<=0,"Under Budget",IF(G13<=5%,"Within Budget",IF(G13<=15%,"Slightly Over","Significantly Over"))) -> Under Budget
... A1513: 45992 | B1513: Operations | C1513: Taxes | D1513: 5838.96 | E1513: 5481.56 | F1513: =E1513-D1513 -> -357.4 | G1513: =IFERROR(F1513/D1513,0) -> -0.06120953 | H1513: =IF(G1513<=0,"Under Budget",IF(G1513<=5%,"Within Budget",IF(G1513<=15%,"Slightly Over","Significantly Over"))) -> Under Budget

Sheet Expense_Anomaly
A1: Expense_ID | B1: Expense_Date | C1: Department | D1: Category | E1: Actual_Expense | F1: Vendor_ID | G1: Group_Median | H1: Group_MAD | I1: Robust_Z | J1: IF_Anomaly | K1: Anomaly | L1: Variance_vs_Group_Median | M1: Risk_Level
A2: EXP-500001 | B2: 45292 | C2: IT | D2: Salaries | E2: 95356.73 | F2: VEND-121 | G2: 110154.51 | H2: 11029.19 | I2: -0.9049715 | J2: -1 | K2: Potential Anomaly | L2: -14797.78 | M2: Review
A3: EXP-500064 | B3: 45332 | C3: IT | D3: Salaries | E3: 94170.07 | F3: VEND-107 | G3: 110154.51 | H3: 11029.19 | I3: -0.97754276 | J3: -1 | K3: Potential Anomaly | L3: -15984.44 | M3: Review
A4: EXP-500100 | B4: 45338 | C4: Operations | D4: Salaries | E4: 99065 | F4: VEND-115 | G4: 86979.19 | H4: 8914.815 | I4: 0.91441929 | J4: -1 | K4: Potential Anomaly | L4: 12085.81 | M4: Review
A5: EXP-500127 | B5: 45362 | C5: IT | D5: Salaries | E5: 121526.2 | F5: VEND-145 | G5: 110154.51 | H5: 11029.19 | I5: 0.69544589 | J5: -1 | K5: Potential Anomaly | L5: 11371.69 | M5: Review
A6: EXP-500163 | B6: 45359 | C6: Operations | D6: Salaries | E6: 99503.55 | F6: VEND-147 | G6: 86979.19 | H6: 8914.815 | I6: 0.94760024 | J6: -1 | K6: Potential Anomaly | L6: 12524.36 | M6: Review
A7: EXP-500190 | B7: 45397 | C7: IT | D7: Salaries | E7: 125268.93 | F7: VEND-131 | G7: 110154.51 | H7: 11029.19 | I7: 0.9243359 | J7: -1 | K7: Potential Anomaly | L7: 15114.42 | M7: Review
A8: EXP-500217 | B8: 45391 | C8: Marketing | D8: Salaries | E8: 93521.11 | F8: VEND-117 | G8: 73087.9 | H8: 5096.99 | I8: 2.7039881 | J8: -1 | K8: Potential Anomaly | L8: 20433.21 | M8: Review
A9: EXP-500253 | B9: 45428 | C9: IT | D9: Salaries | E9: 132803.43 | F9: VEND-169 | G9: 110154.51 | H9: 11029.19 | I9: 1.385115 | J9: -1 | K9: Potential Anomaly | L9: 22648.92 | M9: Review
A10: EXP-500289 | B10: 45421 | C10: Operations | D10: Salaries | E10: 108214.3 | F10: VEND-176 | G10: 86979.19 | H10: 8914.815 | I10: 1.6066606 | J10: -1 | K10: Potential Anomaly | L10: 21235.11 | M10: Review
A11: EXP-500316 | B11: 45470 | C11: IT | D11: Salaries | E11: 121631.34 | F11: VEND-148 | G11: 110154.51 | H11: 11029.19 | I11: 0.70187583 | J11: -1 | K11: Potential Anomaly | L11: 11476.83 | M11: Review
A12: EXP-500379 | B12: 45491 | C12: IT | D12: Salaries | E12: 106828.19 | F12: VEND-111 | G12: 110154.51 | H12: 11029.19 | I12: -0.20342408 | J12: -1 | K12: Potential Anomaly | L12: -3326.32 | M12: Review
A13: EXP-500442 | B13: 45520 | C13: IT | D13: Salaries | E13: 99805.33 | F13: VEND-158 | G13: 110154.51 | H13: 11029.19 | I13: -0.63291338 | J13: -1 | K13: Potential Anomaly | L13: -10349.18 | M13: Review
... A36: EXP-501450 | B36: 46002 | C36: IT | D36: Salaries | E36: 113559.73 | F36: VEND-128 | G36: 110154.51 | H36: 11029.19 | I36: 0.20824928 | J36: -1 | K36: Potential Anomaly | L36: 3405.22 | M36: Review

Sheet Cash_Flow
A1: Month | B1: Collections | C1: Other_Income | D1: Cash_Inflows | E1: Cash_Outflows | F1: Net_Cash_Flow | G1: Opening_Cash | H1: Closing_Cash
A2: 45292 | B2: 0 | C2: 0 | D2: 0 | E2: 892257.08 | F2: =D2-E2 -> -892257.08 | G2: 2500000 | H2: =G2+F2 -> 1607742.9
A3: 45323 | B3: 1498657.4 | C3: 23540.173 | D3: 1522197.6 | E3: 952090.14 | F3: =D3-E3 -> 570107.46 | G3: =H2 -> 1607742.9 | H3: =G3+F3 -> 2177850.4
A4: 45352 | B4: 2156419.9 | C4: 71414.733 | D4: 2227834.6 | E4: 1005827.9 | F4: =D4-E4 -> 1222006.7 | G4: =H3 -> 2177850.4 | H4: =G4+F4 -> 3399857
A5: 45383 | B5: 1818535.1 | C5: 59150.341 | D5: 1877685.4 | E5: 1021078.5 | F5: =D5-E5 -> 856606.89 | G5: =H4 -> 3399857 | H5: =G5+F5 -> 4256463.9
A6: 45413 | B6: 2217910.1 | C6: 41466.89 | D6: 2259377 | E6: 999020.26 | F6: =D6-E6 -> 1260356.7 | G6: =H5 -> 4256463.9 | H6: =G6+F6 -> 5516820.7
A7: 45444 | B7: 1754014.9 | C7: 35618.52 | D7: 1789633.4 | E7: 972648.57 | F7: =D7-E7 -> 816984.84 | G7: =H6 -> 5516820.7 | H7: =G7+F7 -> 6333805.5
A8: 45474 | B8: 3112048.1 | C8: 58416.726 | D8: 3170464.8 | E8: 924314.79 | F8: =D8-E8 -> 2246150 | G8: =H7 -> 6333805.5 | H8: =G8+F8 -> 8579955.6
A9: 45505 | B9: 1617432.3 | C9: 47537.453 | D9: 1664969.8 | E9: 843246.09 | F9: =D9-E9 -> 821723.67 | G9: =H8 -> 8579955.6 | H9: =G9+F9 -> 9401679.2
A10: 45536 | B10: 2296144.8 | C10: 45923.303 | D10: 2342068.1 | E10: 853380.45 | F10: =D10-E10 -> 1488687.6 | G10: =H9 -> 9401679.2 | H10: =G10+F10 -> 10890367
A11: 45566 | B11: 1893766.4 | C11: 63685.459 | D11: 1957451.8 | E11: 844573.46 | F11: =D11-E11 -> 1112878.3 | G11: =H10 -> 10890367 | H11: =G11+F11 -> 12003245
A12: 45597 | B12: 2599084.3 | C12: 82008.442 | D12: 2681092.8 | E12: 853375.48 | F12: =D12-E12 -> 1827717.3 | G12: =H11 -> 12003245 | H12: =G12+F12 -> 13830963
A13: 45627 | B13: 2048794.4 | C13: 54842.175 | D13: 2103636.6 | E13: 877812.08 | F13: =D13-E13 -> 1225824.5 | G13: =H12 -> 13830963 | H13: =G13+F13 -> 15056787
A14: 45658 | B14: 2105588.5 | C14: 31960.232 | D14: 2137548.7 | E14: 918898.23 | F14: =D14-E14 -> 1218650.5 | G14: =H13 -> 15056787 | H14: =G14+F14 -> 16275437
... A25: 45992 | B25: 2263449.7 | C25: 65698.333 | D25: 2329148 | E25: 895190.78 | F25: =D25-E25 -> 1433957.2 | G25: =H24 -> 29979181 | H25: =G25+F25 -> 31413139

Sheet Cash_Forecast
A1: Month | B1: Expected_Collections | C1: Forecast_Expenses | D1: Base_Net_Cash_Flow | E1: Base_Closing_Cash | F1: Stress_Net_Cash_Flow | G1: Stress_Closing_Cash | H1: Optimistic_Net_Cash_Flow | I1: Optimistic_Closing_Cash
A2: 46023 | B2: 2130761.3 | C2: 868671.59 | D2: 1262089.7 | E2: 32675228 | F2: 855608.35 | G2: 32268747 | H2: 1561214.6 | I2: 32974353
A3: 46054 | B3: 2130761.3 | C3: 868671.59 | D3: 1262089.7 | E3: 33937318 | F3: 855608.35 | G3: 33124355 | H3: 1561214.6 | I3: 34535568
A4: 46082 | B4: 2130761.3 | C4: 868671.59 | D4: 1262089.7 | E4: 35199408 | F4: 855608.35 | G4: 33979964 | H4: 1561214.6 | I4: 36096782
A5: 46113 | B5: 2130761.3 | C5: 868671.59 | D5: 1262089.7 | E5: 36461497 | F5: 855608.35 | G5: 34835572 | H5: 1561214.6 | I5: 37657997
A6: 46143 | B6: 2130761.3 | C6: 868671.59 | D6: 1262089.7 | E6: 37723587 | F6: 855608.35 | G6: 35691180 | H6: 1561214.6 | I6: 39219212
A7: 46174 | B7: 2130761.3 | C7: 868671.59 | D7: 1262089.7 | E7: 38985677 | F7: 855608.35 | G7: 36546789 | H7: 1561214.6 | I7: 40780426

Sheet KPI_Summary
A1: Metric | B1: Value
A2: Receivable Days | B2: =IFERROR(SUM(Clean_AR_Data!$H:$H)/(SUM(Clean_AR_Data!$F:$F)/365),0) -> 91.664226
A3: Payable Days | B3: 42
A4: Inventory Days | B4: 18
A5: Cash Conversion Cycle | B5: =B2+B3-B4 -> 115.66423
A6: Collection Efficiency % | B6: 74.886513
A7: Overdue AR | B7: 17303752
A8: Closing Cash | B8: 31413139
A9: Budget Overrun % | B9: 0
A10: Negative Cash Flow Months | B10: 1
A11: Liquidity Risk Score | B11: =MIN(100,ROUND((B2>90)*35+(B2>60)*(B2<=90)*25+(B7>0)*(B7/SUM(Clean_AR_Data!$H:$H)>30%)*25+(B6<70%)*20,0)) -> 60
A12: Liquidity Risk Level | B12: =IF(B11>=70,"High",IF(B11>=40,"Medium","Low")) -> Medium

Sheet Expense_Analysis
A1: EXPENSE ANALYSIS ENGINE | P1: Departments | Q1: Categories | R1: Months
P2: department | Q2: Category
A3: MONTHLY EXPENSE TREND | E3: CATEGORY-WISE EXPENSE | I3: DEPARTMENT-WISE EXPENSE | P3: Administration | Q3: Marketing | R3: 45292
A4: Month | B4: Expense | C4: MoM Growth | E4: Category | F4: Expense | G4: % Total | I4: Department | J4: Expense | K4: % Total | P4: Finance | Q4: Operations | R4: 45323
A5: =DATE(YEAR(MIN(Clean_Expenses!$B:$B)),1,1) -> 45292 | B5: =IF(OR(Dashboard!$D$4="All Months",TEXT(A5,"mmm-yy")=TEXT(Dashboard!$D$4,"mmm-yy")),SUMIFS(Clean_Expenses!$E:$E,Clean_Expenses!$B:$B,">="&A5,Clean_Expenses!$B:$B,"<"&EDATE(A5,1)),0) -> 0 | C5: ="" | E5: Marketing | F5: =IF(OR(Dashboard!$J$4="All Categories",E5=Dashboard!$J$4),SUMIFS(Clean_Expenses!$E:$E,Clean_Expenses!$D:$D,E5),0) -> 1779638 | G5: =IFERROR(F5/SUM($F$5:$F$13),0) -> 0.080713668 | I5: Administration | J5: =IF(OR(Dashboard!$G$4="All Departments",I5=Dashboard!$G$4),SUMIFS(Clean_Expenses!$E:$E,Clean_Expenses!$C:$C,I5),0) -> 2027783.9 | K5: =IFERROR(J5/SUM($J$5:$J$11),0) -> 0.09196807 | P5: HR | Q5: Other | R5: 45352
A6: =DATE(YEAR(MIN(Clean_Expenses!$B:$B)),2,1) -> 45323 | B6: =IF(OR(Dashboard!$D$4="All Months",TEXT(A6,"mmm-yy")=TEXT(Dashboard!$D$4,"mmm-yy")),SUMIFS(Clean_Expenses!$E:$E,Clean_Expenses!$B:$B,">="&A6,Clean_Expenses!$B:$B,"<"&EDATE(A6,1)),0) -> 0 | C6: =IFERROR(B6/B5-1,0) -> 0 | E6: Operations | F6: =IF(OR(Dashboard!$J$4="All Categories",E6=Dashboard!$J$4),SUMIFS(Clean_Expenses!$E:$E,Clean_Expenses!$D:$D,E6),0) -> 1754240.3 | G6: =IFERROR(F6/SUM($F$5:$F$13),0) -> 0.079561779 | I6: Finance | J6: =IF(OR(Dashboard!$G$4="All Departments",I6=Dashboard!$G$4),SUMIFS(Clean_Expenses!$E:$E,Clean_Expenses!$C:$C,I6),0) -> 1814899.1 | K6: =IFERROR(J6/SUM($J$5:$J$11),0) -> 0.082312898 | P6: IT | Q6: Rent | R6: 45383
A7: =DATE(YEAR(MIN(Clean_Expenses!$B:$B)),3,1) -> 45352 | B7: =IF(OR(Dashboard!$D$4="All Months",TEXT(A7,"mmm-yy")=TEXT(Dashboard!$D$4,"mmm-yy")),SUMIFS(Clean_Expenses!$E:$E,Clean_Expenses!$B:$B,">="&A7,Clean_Expenses!$B:$B,"<"&EDATE(A7,1)),0) -> 0 | C7: =IFERROR(B7/B6-1,0) -> 0 | E7: Other | F7: =IF(OR(Dashboard!$J$4="All Categories",E7=Dashboard!$J$4),SUMIFS(Clean_Expenses!$E:$E,Clean_Expenses!$D:$D,E7),0) -> 657455.58 | G7: =IFERROR(F7/SUM($F$5:$F$13),0) -> 0.029818227 | I7: HR | J7: =IF(OR(Dashboard!$G$4="All Departments",I7=Dashboard!$G$4),SUMIFS(Clean_Expenses!$E:$E,Clean_Expenses!$C:$C,I7),0) -> 2190418 | K7: =IFERROR(J7/SUM($J$5:$J$11),0) -> 0.099344173 | P7: Marketing | Q7: Salaries | R7: 45413
A8: =DATE(YEAR(MIN(Clean_Expenses!$B:$B)),4,1) -> 45383 | B8: =IF(OR(Dashboard!$D$4="All Months",TEXT(A8,"mmm-yy")=TEXT(Dashboard!$D$4,"mmm-yy")),SUMIFS(Clean_Expenses!$E:$E,Clean_Expenses!$B:$B,">="&A8,Clean_Expenses!$B:$B,"<"&EDATE(A8,1)),0) -> 0 | C8: =IFERROR(B8/B7-1,0) -> 0 | E8: Rent | F8: =IF(OR(Dashboard!$J$4="All Categories",E8=Dashboard!$J$4),SUMIFS(Clean_Expenses!$E:$E,Clean_Expenses!$D:$D,E8),0) -> 2184651.6 | G8: =IFERROR(F8/SUM($F$5:$F$13),0) -> 0.099082643 | I8: IT | J8: =IF(OR(Dashboard!$G$4="All Departments",I8=Dashboard!$G$4),SUMIFS(Clean_Expenses!$E:$E,Clean_Expenses!$C:$C,I8),0) -> 5119961.5 | K8: =IFERROR(J8/SUM($J$5:$J$11),0) -> 0.23221063 | P8: Operations | Q8: Software | R8: 45444
A9: =DATE(YEAR(MIN(Clean_Expenses!$B:$B)),5,1) -> 45413 | B9: =IF(OR(Dashboard!$D$4="All Months",TEXT(A9,"mmm-yy")=TEXT(Dashboard!$D$4,"mmm-yy")),SUMIFS(Clean_Expenses!$E:$E,Clean_Expenses!$B:$B,">="&A9,Clean_Expenses!$B:$B,"<"&EDATE(A9,1)),0) -> 0 | C9: =IFERROR(B9/B8-1,0) -> 0 | E9: Salaries | F9: =IF(OR(Dashboard!$J$4="All Categories",E9=Dashboard!$J$4),SUMIFS(Clean_Expenses!$E:$E,Clean_Expenses!$D:$D,E9),0) -> 11074963 | G9: =IFERROR(F9/SUM($F$5:$F$13),0) -> 0.50229366 | I9: Marketing | J9: =IF(OR(Dashboard!$G$4="All Departments",I9=Dashboard!$G$4),SUMIFS(Clean_Expenses!$E:$E,Clean_Expenses!$C:$C,I9),0) -> 3519337.4 | K9: =IFERROR(J9/SUM($J$5:$J$11),0) -> 0.15961596 | P9: Sales | Q9: Taxes | R9: 45474
A10: =DATE(YEAR(MIN(Clean_Expenses!$B:$B)),6,1) -> 45444 | B10: =IF(OR(Dashboard!$D$4="All Months",TEXT(A10,"mmm-yy")=TEXT(Dashboard!$D$4,"mmm-yy")),SUMIFS(Clean_Expenses!$E:$E,Clean_Expenses!$B:$B,">="&A10,Clean_Expenses!$B:$B,"<"&EDATE(A10,1)),0) -> 0 | C10: =IFERROR(B10/B9-1,0) -> 0 | E10: Software | F10: =IF(OR(Dashboard!$J$4="All Categories",E10=Dashboard!$J$4),SUMIFS(Clean_Expenses!$E:$E,Clean_Expenses!$D:$D,E10),0) -> 1760247 | G10: =IFERROR(F10/SUM($F$5:$F$13),0) -> 0.079834208 | I10: Operations | J10: =IF(OR(Dashboard!$G$4="All Departments",I10=Dashboard!$G$4),SUMIFS(Clean_Expenses!$E:$E,Clean_Expenses!$C:$C,I10),0) -> 4236564.5 | K10: =IFERROR(J10/SUM($J$5:$J$11),0) -> 0.19214506 | Q10: Travel | R10: 45505
A11: =DATE(YEAR(MIN(Clean_Expenses!$B:$B)),7,1) -> 45474 | B11: =IF(OR(Dashboard!$D$4="All Months",TEXT(A11,"mmm-yy")=TEXT(Dashboard!$D$4,"mmm-yy")),SUMIFS(Clean_Expenses!$E:$E,Clean_Expenses!$B:$B,">="&A11,Clean_Expenses!$B:$B,"<"&EDATE(A11,1)),0) -> 924314.79 | C11: =IFERROR(B11/B10-1,0) -> 0 | E11: Taxes | F11: =IF(OR(Dashboard!$J$4="All Categories",E11=Dashboard!$J$4),SUMIFS(Clean_Expenses!$E:$E,Clean_Expenses!$D:$D,E11),0) -> 659136.8 | G11: =IFERROR(F11/SUM($F$5:$F$13),0) -> 0.029894477 | I11: Sales | J11: =IF(OR(Dashboard!$G$4="All Departments",I11=Dashboard!$G$4),SUMIFS(Clean_Expenses!$E:$E,Clean_Expenses!$C:$C,I11),0) -> 3139817.2 | K11: =IFERROR(J11/SUM($J$5:$J$11),0) -> 0.14240321 | Q11: Utilities | R11: 45536
A12: =DATE(YEAR(MIN(Clean_Expenses!$B:$B)),8,1) -> 45505 | B12: =IF(OR(Dashboard!$D$4="All Months",TEXT(A12,"mmm-yy")=TEXT(Dashboard!$D$4,"mmm-yy")),SUMIFS(Clean_Expenses!$E:$E,Clean_Expenses!$B:$B,">="&A12,Clean_Expenses!$B:$B,"<"&EDATE(A12,1)),0) -> 0 | C12: =IFERROR(B12/B11-1,0) -> -1 | E12: Travel | F12: =IF(OR(Dashboard!$J$4="All Categories",E12=Dashboard!$J$4),SUMIFS(Clean_Expenses!$E:$E,Clean_Expenses!$D:$D,E12),0) -> 1071176.4 | G12: =IFERROR(F12/SUM($F$5:$F$13),0) -> 0.048582111 | R12: 45566
A13: =DATE(YEAR(MIN(Clean_Expenses!$B:$B)),9,1) -> 45536 | B13: =IF(OR(Dashboard!$D$4="All Months",TEXT(A13,"mmm-yy")=TEXT(Dashboard!$D$4,"mmm-yy")),SUMIFS(Clean_Expenses!$E:$E,Clean_Expenses!$B:$B,">="&A13,Clean_Expenses!$B:$B,"<"&EDATE(A13,1)),0) -> 0 | C13: =IFERROR(B13/B12-1,0) -> 0 | E13: Utilities | F13: =IF(OR(Dashboard!$J$4="All Categories",E13=Dashboard!$J$4),SUMIFS(Clean_Expenses!$E:$E,Clean_Expenses!$D:$D,E13),0) -> 1107272.8 | G13: =IFERROR(F13/SUM($F$5:$F$13),0) -> 0.050219229 | R13: 45597
A14: =DATE(YEAR(MIN(Clean_Expenses!$B:$B)),10,1) -> 45566 | B14: =IF(OR(Dashboard!$D$4="All Months",TEXT(A14,"mmm-yy")=TEXT(Dashboard!$D$4,"mmm-yy")),SUMIFS(Clean_Expenses!$E:$E,Clean_Expenses!$B:$B,">="&A14,Clean_Expenses!$B:$B,"<"&EDATE(A14,1)),0) -> 0 | C14: =IFERROR(B14/B13-1,0) -> 0 | R14: 45627
A15: =DATE(YEAR(MIN(Clean_Expenses!$B:$B)),11,1) -> 45597 | B15: =IF(OR(Dashboard!$D$4="All Months",TEXT(A15,"mmm-yy")=TEXT(Dashboard!$D$4,"mmm-yy")),SUMIFS(Clean_Expenses!$E:$E,Clean_Expenses!$B:$B,">="&A15,Clean_Expenses!$B:$B,"<"&EDATE(A15,1)),0) -> 0 | C15: =IFERROR(B15/B14-1,0) -> 0
A16: =DATE(YEAR(MIN(Clean_Expenses!$B:$B)),12,1) -> 45627 | B16: =IF(OR(Dashboard!$D$4="All Months",TEXT(A16,"mmm-yy")=TEXT(Dashboard!$D$4,"mmm-yy")),SUMIFS(Clean_Expenses!$E:$E,Clean_Expenses!$B:$B,">="&A16,Clean_Expenses!$B:$B,"<"&EDATE(A16,1)),0) -> 0 | C16: =IFERROR(B16/B15-1,0) -> 0

Sheet Dashboard_Lists
A1: Month List | B1: Department List | C1: Category List
A2: All Months | B2: All Departments | C2: All Categories
A3: 45292 | B3: Administration | C3: Marketing
A4: 45323 | B4: Finance | C4: Operations
A5: 45352 | B5: HR | C5: Other
A6: 45383 | B6: IT | C6: Rent
A7: 45413 | B7: Marketing | C7: Salaries
A8: 45444 | B8: Operations | C8: Software
A9: 45474 | B9: Sales | C9: Taxes
A10: 45505 | C10: Travel
A11: 45536 | C11: Utilities
A12: 45566
A13: 45597
A14: 45627
A15: 45658
A16: 45689
A17: 45717
A18: 45748
A19: 45778
A20: 45809
A21: 45839
A22: 45870
A23: 45901
... A26: 45992
